Workbook
Name \0: #REF!
Name \a: #REF!
Name \b: #N/A
Name \d: #REF!
Name \L: #REF!
Name \m: #REF!
Name \N: #REF!
Name \O: #REF!
Name \p: #N/A
Name \Q: #REF!
Name \r: #REF!
Name \s: #REF!
Name \t: #REF!
Name \V: #REF!
Name \x: #REF!
Name \y: #REF!
Name \z: #REF!
Name _: #REF!
Name _.5_160: #REF!
Name _.5_80: #REF!
Name _.5_XXS: #REF!
Name _.75_160: #REF!
Name _.75_80: #REF!
Name _.75_XXS: #REF!
Name _____BAC110: #REF!
Name _____BAC120: #REF!
Name _____BAC125: #REF!
Name _____BAC130: #REF!
Name _____BAC135: #REF!
Name _____BAC140: #REF!
Name _____BAC145: #REF!
Name _____BAC150: #REF!
Name _____BAC155: #REF!
Name _____BAC160: #REF!
Name _____BAC165: #REF!
Name _____BAC170: #REF!
Name _____BAC180: #REF!
Name _____BAC190: #REF!
Name _____NGd1: #REF!
Name _____NGd10: #REF!
Name _____NGd12: #REF!
Name _____NGd13: #REF!
Name _____NGd14: #REF!
Name _____NGd15: #REF!
Name _____NGd2: #REF!
Name _____NGd3: #REF!
Name _____NGd4: #REF!
Name _____NGd5: #REF!
Name _____NGd6: #REF!
Name _____NGd7: #REF!
Name _____NGd8: #REF!
Name _____NGd9: #REF!
Name _____NPa1: #REF!
Name _____NPa10: #REF!
Name _____NPa2: #REF!
Name _____NPa3: #REF!
Name _____NPa4: #REF!
Name _____NPa5: #REF!
Name _____NPa6: #REF!
Name _____NPa7: #REF!

Sheet БАЛАНС РУКОВОДСТВУ руб. с НДС
A1: № п/п | B1: НАИМЕПодрядчик 4НИЕ | C1: Подрядчик 1 | D1: Подрядчик 1 | E1: Подрядчик 1 | F1: Подрядчик 2 | G1: Подрядчик 2 | H1: Подрядчик 2 | I1: Подрядчик 3 | J1: Подрядчик 3 | K1: Подрядчик 3 | L1: Подрядчик 3 | M1: Подрядчик 4 | N1: Подрядчик 5 | O1: Подрядчик 6 | P1: Подрядчик 6 | Q1: Подрядчик 6 | R1: Подрядчик 7 | T1: Прочие подрядчики | U1: Подрядчик 8 | V1: Подрядчик 9 | W1: Подрядчик 10 | X1: Подрядчик 10 | Y1: Подрядчик 10 | Z1: Подрядчик 11 | AA1: Подрядчик 12 | AB1: Подрядчик 13 | AC1: Подрядчик 11 | AD1: Подрядчик 14 | AE1: Подрядчик 15 | AF1: Подрядчик 15 | AG1: Подрядчик 15 | AH1: Подрядчик 16 | AI1: Подрядчик 17 | AJ1: Подрядчик 18 | AK1: Подрядчик 18 | AL1: Подрядчик 19 | AM1: Подрядчик 20 | AN1: Подрядчик 21 | AO1: Подрядчик 22 | AP1: Подрядчик 23 | AQ1: Подрядчик 24 | AR1: млн руб. с НДС | AS1: дата актуальности НЗП | AT1: ='Преза НЗП без НДС'!AO1 -> 46280
B2: договор | D2: Дог.9756 | E2: Дог.10675 | G2: Дог.10221 | H2: Дог.11996 | J2: Дог.10321 | K2: Дог.10321-5 | L2: Дог.11980 | M2: Дог.10539 | N2: Дог.10988 | P2: Дог.7449-10 | Q2: Дог.11458 | R2: Дог.12009 | U2: Дог.7038 | V2: Дог.7043 | X2: Дог.8833 | Y2: Дог.9211 | AA2: Дог.8713 | AB2: НГ.12 | AC2: Дог.8714 | AD2: Дог.6016 | AF2: Дог.7766 | AG2: Дог.7766-2 | AH2: Дог.10434 | AI2: Дог.11820 | AJ2: Дог.10144 | AK2: Дог.10148 | AL2: Дог.9305-1 | AM2: Дог.7151 | AN2: Дог.10619 | AO2: Дог.10937 | AP2: Дог.8172 | AQ2: Дог.10274
B3: вид работ/проект | C3: Монолит и ММР | D3: Монолит | E3: ММР ЭМР | F3: Монолит и ММР | G3: монолит ПС и ОЗХ | H3: ММР ПС | I3: Генподряд, резервуары ГП | J3: ГП мПЭ | K3: Объект 2: Изъятые объемы у Ямата по тит 1401 | L3: Резервуары готовой продукци | M3: Эстакады ОЗХ | N3: Склад ГП | O3: Водооборотный цикл, резервуары сырья | P3: Врезки в действующие трубопроводы | Q3: Водооборотный цикл | R3: Подстанции и сети | U3: СЦ | V3: СЦ | X3: СЦ | Y3: ПЭ | AA3: ЭБСМ | AB3: ПС и ОЗХ | AC3: ПЭ | AF3: СЦ | AG3: ПЭ | AI3: Монтаж МК | AP3: Объемы Ямата по ОЗХ | AQ3: Цех префабрикации
B4: курс | D4: 89.79 | E4: 80 | G4: 91.5 | H4: 80 | J4: 80 | K4: 80 | L4: 85 | M4: 1 | N4: 1 | P4: 1 | Q4: 1 | U4: 1 | V4: 1 | X4: 1 | Y4: 1 | AA4: 1 | AB4: 1 | AC4: 1 | AD4: 1 | AF4: 1 | AG4: 1 | AH4: 1 | AI4: 80 | AJ4: 1 | AK4: 1 | AL4: 1 | AM4: 1 | AN4: 1 | AO4: 1 | AP4: 1 | AQ4: 1
A5: 1.1. | B5: Стоимость работ по контракту (подписано) | C5: =D5+E5 -> 23643.905 | D5: 7005.2222 | E5: 16638.683 | F5: =G5+H5 -> 18723.24 | G5: 8538.2466 | H5: 10184.993 | I5: =J5+K5+L5 -> 9183.9918 | J5: 7362.3109 | K5: 100.92962 | L5: 1720.7512 | M5: 11079.096 | N5: 3212.3523 | O5: =P5+Q5 -> 3637.0038 | P5: 47.107459 | Q5: 3589.8964 | R5: 3564.4619 | T5: =U5+V5+W5+Z5+AD5+AE5+AH5+AI5+AJ5+AK5+AL5+AM5+AN5+AO5+AQ5 -> 7507.4812 | U5: 987.58487 | V5: 480.19318 | W5: =X5+Y5 -> 956.16997 | X5: 357.37751 | Y5: 598.79246 | Z5: =SUM(AA5:AC5) -> 475.86051 | AA5: 71.635276 | AB5: 131.05557 | AC5: 273.16967 | AD5: 687.96021 | AE5: =AF5+AG5 -> 639.72509 | AF5: 599.85461 | AG5: 39.870475 | AH5: 384.72912 | AI5: 85.160542 | AJ5: 121.034 | AK5: 41.626364 | AL5: 49.199584 | AM5: 19.942107 | AN5: 26.397624 | AO5: 280.74915 | AP5: 203.31445 | AQ5: 2271.1489
A6: 1.2. | B6: Стоимость работ по контракту (прогноз) | C6: =D6+E6 -> 20960.906 | D6: =HLOOKUP(D2,'Преза НЗП без НДС'!$E$2:$AL$5,4,0)*1.22 -> 7571.5154 | E6: =HLOOKUP(E2,'Преза НЗП без НДС'!$E$2:$AL$5,4,0)*1.22 -> 13389.391 | F6: =G6+H6 -> 18790.589 | G6: =HLOOKUP(G2,'Преза НЗП без НДС'!$E$2:$AL$5,4,0)*1.22 -> 8558.3272 | H6: =HLOOKUP(H2,'Преза НЗП без НДС'!$E$2:$AL$5,4,0)*1.22 -> 10232.262 | I6: =J6+K6+L6 -> 10000.805 | J6: =HLOOKUP(J2,'Преза НЗП без НДС'!$E$2:$AL$5,4,0)*1.22 -> 7561.6005 | K6: =HLOOKUP(K2,'Преза НЗП без НДС'!$E$2:$AL$5,4,0)*1.22 -> 123.13414 | L6: =HLOOKUP(L2,'Преза НЗП без НДС'!$E$2:$AL$5,4,0)*1.22 -> 2316.07 | M6: =HLOOKUP(M2,'Преза НЗП без НДС'!$E$2:$AL$5,4,0)*1.22 -> 11115.316 | N6: =HLOOKUP(N2,'Преза НЗП без НДС'!$E$2:$AL$5,4,0)*1.22 -> 5546.8811 | O6: =P6+Q6 -> 3723.3917 | P6: =IFERROR(HLOOKUP(P2,'Преза НЗП без НДС'!$E$2:$AL$5,4,0)*1.22,P5) -> 47.107459 | Q6: =HLOOKUP(Q2,'Преза НЗП без НДС'!$E$2:$AL$5,4,0)*1.22 -> 3676.2843 | R6: =HLOOKUP(R2,'Преза НЗП без НДС'!$E$2:$AL$5,4,0)*1.22 -> 3564.4619 | T6: =U6+V6+W6+Z6+AD6+AE6+AH6+AI6+AJ6+AK6+AL6+AM6+AN6+AO6+AQ6 -> 8341.1554 | U6: =HLOOKUP(U2,'Преза НЗП без НДС'!$E$2:$AL$5,4,0)*1.22 -> 1388.2405 | V6: =HLOOKUP(V2,'Преза НЗП без НДС'!$E$2:$AL$5,4,0)*1.22 -> 512.18369 | W6: =X6+Y6 -> 1213.7648 | X6: =HLOOKUP(X2,'Преза НЗП без НДС'!$E$2:$AL$5,4,0)*1.22 -> 606.88239 | Y6: =HLOOKUP(Y2,'Преза НЗП без НДС'!$E$2:$AL$5,4,0)*1.22 -> 606.88239 | Z6: =SUM(AA6:AC6) -> 275.23226 | AA6: =HLOOKUP(AA2,'Преза НЗП без НДС'!$E$2:$AL$5,4,0)*1.22 -> 71.635276 | AB6: =HLOOKUP(AB2,'Преза НЗП без НДС'!$E$2:$AL$5,4,0)*1.22 -> 116.13757 | AC6: =HLOOKUP(AC2,'Преза НЗП без НДС'!$E$2:$AL$5,4,0)*1.22 -> 87.459415 | AD6: =HLOOKUP(AD2,'Преза НЗП без НДС'!$E$2:$AL$5,4,0)*1.22 -> 836.77456 | AE6: =AF6+AG6 -> 768.23369 | AF6: =HLOOKUP(AF2,'Преза НЗП без НДС'!$E$2:$AL$5,4,0)*1.22 -> 728.36321 | AG6: =HLOOKUP(AG2,'Преза НЗП без НДС'!$E$2:$AL$5,4,0)*1.22 -> 39.870475 | AH6: =HLOOKUP(AH2,'Преза НЗП без НДС'!$E$2:$AL$5,4,0)*1.22 -> 386.32871 | AI6: =IFERROR(HLOOKUP(AI2,'Преза НЗП без НДС'!$E$2:$AL$5,4,0)*1.22,AI5) -> 85.160542 | AJ6: =HLOOKUP(AJ2,'Преза НЗП без НДС'!$E$2:$AL$5,4,0)*1.22 -> 175.86878 | AK6: =HLOOKUP(AK2,'Преза НЗП без НДС'!$E$2:$AL$5,4,0)*1.22 -> 41.626364 | AL6: =HLOOKUP(AL2,'Преза НЗП без НДС'!$E$2:$AL$5,4,0)*1.22 -> 49.562887 | AM6: =IFERROR(HLOOKUP(AM2,'Преза НЗП без НДС'!$E$2:$AL$5,4,0)*1.22,AM5) -> 19.942107 | AN6: =HLOOKUP(AN2,'Преза НЗП без НДС'!$E$2:$AL$5,4,0)*1.22 -> 36.338471 | AO6: =HLOOKUP(AO2,'Преза НЗП без НДС'!$E$2:$AL$5,4,0)*1.22 -> 280.74915 | AP6: =HLOOKUP(AP2,'Преза НЗП без НДС'!$E$2:$AL$5,4,0)*1.22 -> 443.58456 | AQ6: =IFERROR(HLOOKUP(AQ2,'Преза НЗП без НДС'!$E$2:$AL$5,4,0)*1.22,AQ5) -> 2271.1489
A7: 2 | B7: Выполнение всего, в том числе | C7: =D7+E7 -> 7151.5679 | D7: =D8+D10 -> 5228.9532 | E7: =E8+E10 -> 1922.6148 | F7: =G7+H7 -> 7783.2615 | G7: =G8+G10 -> 6226.2029 | H7: =H8+H10 -> 1557.0586 | I7: =J7+K7+L7 -> 3081.2625 | J7: =J8+J10+J9 -> 2475.9024 | K7: =K8+K10 -> 74.317511 | L7: =L8+L10 -> 531.04266 | M7: =M8+M10 -> 2767.0679 | N7: =N8+N10 -> 1482.5106 | O7: =P7+Q7 -> 715.23872 | P7: =P8+P10 -> 16.807455 | Q7: =Q8+Q10 -> 698.43127 | R7: =R8+R10 -> 100.5697 | T7: =U7+V7+W7+Z7+AD7+AE7+AH7+AI7+AJ7+AK7+AL7+AM7+AN7+AO7+AQ7 -> 6025.1429 | U7: =U8+U10 -> 939.4 | V7: =V8+V10 -> 410.00452 | W7: =X7+Y7 -> 1606.42 | X7: =X8+X10 -> 1163.4672 | Y7: =Y8+Y10 -> 442.95284 | Z7: =SUM(AA7:AC7) -> 262.2864 | AA7: =AA8+AA10 -> 67.187522 | AB7: =AB8+AB10 -> 107.81683 | AC7: =AC8+AC10 -> 87.282049 | AD7: =AD8+AD10 -> 830.82 | AE7: =AF7+AG7 -> 731.71451 | AF7: =AF8+AF10 -> 687.79817 | AG7: =AG8+AG10 -> 43.916338 | AH7: =AH8+AH10 -> 384.3 | AI7: =AI8+AI10 -> 9.7562931 | AJ7: =AJ8+AJ10 -> 125.66 | AK7: =AK8+AK10 -> 56.191687 | AL7: =AL8+AL10 -> 62.22 | AM7: =AM8+AM10 -> 19.900724 | ... AQ7: =AQ8+AQ10 -> 552.39558
A8: 2.1. | B8: Принято (КС-2) | C8: =D8+E8 -> 6390.6754 | D8: 4797.8536 | E8: 1592.8217 | F8: =G8+H8 -> 6749.4103 | G8: 5447.313 | H8: 1302.0973 | I8: =J8+K8+L8 -> 2461.6888 | J8: 1936.3042 | K8: 74.317511 | L8: 451.06712 | M8: 2118.671 | N8: 1304.8525 | O8: =P8+Q8 -> 544.09086 | P8: 16.807455 | Q8: 527.28341 | R8: 24.028867 | T8: =U8+V8+W8+Z8+AD8+AE8+AH8+AI8+AJ8+AK8+AL8+AM8+AN8+AO8+AQ8 -> 5856.5913 | U8: 797.73984 | V8: 404.61471 | W8: =X8+Y8 -> 1606.42 | X8: 1163.4672 | Y8: 442.95284 | Z8: =SUM(AA8:AC8) -> 257.88061 | AA8: 66.638753 | AB8: 105.39066 | AC8: 85.8512 | AD8: 817.89874 | AE8: =AF8+AG8 -> 731.0609 | AF8: 687.79817 | AG8: 43.262724 | AH8: 382.4427 | AI8: 9.7562931 | AJ8: 124.52961 | AK8: 56.191687 | AL8: 61.68677 | AM8: 19.900724 | AN8: 21.930053 | AO8: 12.143121 | AP8: 189.20867 | AQ8: 552.39558
A9: 2.2. | B9: Курсовая разница на приемку | D9: =-+(D8-D13-D20+D33)-'Баланс ФЭК (валюта) с НДС'!E25*'Баланс ФЭК (валюта) с НДС'!E4 -> -5.2289945e-07 | E9: =-+(E8-E13-E20+E33)-'Баланс ФЭК (валюта) с НДС'!F25*'Баланс ФЭК (валюта) с НДС'!F4 -> -4.9634261 | G9: =-+(G8-G13-G20+G33)-'Баланс ФЭК (валюта) с НДС'!G25*'Баланс ФЭК (валюта) с НДС'!G4 -> -1.56394e-05 | H9: =-+(H8-H13-H20+H33)-'Баланс ФЭК (валюта) с НДС'!H25*'Баланс ФЭК (валюта) с НДС'!H4 -> -16.194227 | I9: =J9+K9+L9 -> 6.0184066 | J9: =-+(J8-J13-J20+J33)-'Баланс ФЭК (валюта) с НДС'!I25*'Баланс ФЭК (валюта) с НДС'!I4 -> 0.85709687 | K9: =-+(K8-K13-K20+K33)-'Баланс ФЭК (валюта) с НДС'!J25*'Баланс ФЭК (валюта) с НДС'!J4 -> 2.8088643e-14 | L9: =-+(L8-L13-L20+L33)-'Баланс ФЭК (валюта) с НДС'!K25*'Баланс ФЭК (валюта) с НДС'!K4 -> 5.1613098 | T9: =U9+V9+W9+Z9+AD9+AE9+AH9+AI9+AJ9+AK9+AL9+AM9+AN9+AO9+AQ9 -> 0
A10: 2.3. | B10: НЗП | C10: =D10+E10 -> 760.89255 | D10: =IF((D11-D8)<0,,D11-D8) -> 431.09952 | E10: =IF((E11-E8)<0,,E11-E8) -> 329.79304 | F10: =G10+H10 -> 1033.8513 | G10: =IF((G11-G8)<0,,G11-G8) -> 778.8899 | H10: =IF((H11-H8)<0,,H11-H8) -> 254.96136 | I10: =J10+K10+L10 -> 618.71663 | J10: =IF((J11-J8)<0,,J11-J8) -> 538.74109 | K10: =IF((K11-K8)<0,,K11-K8) -> 0 | L10: =IF((L11-L8)<0,,L11-L8) -> 79.975538 | M10: =IF((M11-M8)<0,,M11-M8) -> 648.39689 | N10: =IF((N11-N8)<0,,N11-N8) -> 177.65806 | O10: =P10+Q10 -> 171.14786 | P10: =IF((P11-P8)<0,,P11-P8) -> 0 | Q10: =IF((Q11-Q8)<0,,Q11-Q8) -> 171.14786 | R10: =IF((R11-R8)<0,,R11-R8) -> 76.540837 | T10: =U10+V10+W10+Z10+AD10+AE10+AH10+AI10+AJ10+AK10+AL10+AM10+AN10+AO10+AQ10 -> 168.55156 | U10: =IF((U11-U8)<0,,U11-U8) -> 141.66016 | V10: =IF((V11-V8)<0,,V11-V8) -> 5.3898128 | W10: =X10+Y10 -> 0 | X10: =IF((X11-X8)<0,,X11-X8) -> 0 | Y10: =IF((Y11-Y8)<0,,Y11-Y8) -> 0 | Z10: =SUM(AA10:AC10) -> 4.4057904 | AA10: =IF((AA11-AA8)<0,,AA11-AA8) -> 0.54876848 | AB10: =IF((AB11-AB8)<0,,AB11-AB8) -> 2.4261734 | AC10: =IF((AC11-AC8)<0,,AC11-AC8) -> 1.4308485 | AD10: =IF((AD11-AD8)<0,,AD11-AD8) -> 12.921264 | AE10: =AF10+AG10 -> 0.65361434 | AF10: =IF((AF11-AF8)<0,,AF11-AF8) -> 0 | AG10: =IF((AG11-AG8)<0,,AG11-AG8) -> 0.65361434 | AH10: =IF((AH11-AH8)<0,,AH11-AH8) -> 1.8573003 | AI10: =IF((AI11-AI8)<0,,AI11-AI8) -> 0 | AJ10: =IF((AJ11-AJ8)<0,,AJ11-AJ8) -> 1.1303883 | AK10: =IF((AK11-AK8)<0,,AK11-AK8) -> 0 | AL10: =IF((AL11-AL8)<0,,AL11-AL8) -> 0.53323009 | AM10: =IF((AM11-AM8)<0,,AM11-AM8) -> 0 | ... AQ10: =IF((AQ11-AQ8)<0,,AQ11-AQ8) -> 0
B11: Выполнено всего из отчета НЗП | D11: =IFERROR(HLOOKUP(D2,'Преза НЗП без НДС'!$E$2:$AL$6,5,0)*1.22,D8) -> 5228.9532 | E11: =IFERROR(HLOOKUP(E2,'Преза НЗП без НДС'!$E$2:$AL$6,5,0)*1.22,E8) -> 1922.6148 | G11: =IFERROR(HLOOKUP(G2,'Преза НЗП без НДС'!$E$2:$AL$6,5,0)*1.22,G8) -> 6226.2029 | H11: =IFERROR(HLOOKUP(H2,'Преза НЗП без НДС'!$E$2:$AL$6,5,0)*1.22,H8) -> 1557.0586 | J11: =IFERROR(HLOOKUP(J2,'Преза НЗП без НДС'!$E$2:$AL$6,5,0)*1.22,J8) -> 2475.0453 | K11: =IFERROR(HLOOKUP(K2,'Преза НЗП без НДС'!$E$2:$AL$6,5,0)*1.22,K8) -> 71.524037 | L11: =IFERROR(HLOOKUP(L2,'Преза НЗП без НДС'!$E$2:$AL$6,5,0)*1.22,L8) -> 531.04266 | M11: =IFERROR(HLOOKUP(M2,'Преза НЗП без НДС'!$E$2:$AL$6,5,0)*1.22,M8) -> 2767.0679 | N11: =IFERROR(HLOOKUP(N2,'Преза НЗП без НДС'!$E$2:$AL$6,5,0)*1.22,N8) -> 1482.5106 | P11: =IFERROR(HLOOKUP(P2,'Преза НЗП без НДС'!$E$2:$AL$6,5,0)*1.22,P8) -> 16.807455 | Q11: =IFERROR(HLOOKUP(Q2,'Преза НЗП без НДС'!$E$2:$AL$6,5,0)*1.22,Q8) -> 698.43127 | R11: =IFERROR(HLOOKUP(R2,'Преза НЗП без НДС'!$E$2:$AL$6,5,0)*1.22,R8) -> 100.5697 | U11: =IFERROR(HLOOKUP(U2,'Преза НЗП без НДС'!$E$2:$AL$6,5,0)*1.22,U8) -> 939.4 | V11: =IFERROR(HLOOKUP(V2,'Преза НЗП без НДС'!$E$2:$AL$6,5,0)*1.22,V8) -> 410.00452 | X11: =IFERROR(HLOOKUP(X2,'Преза НЗП без НДС'!$E$2:$AL$6,5,0)*1.22,X8) -> 447.74141 | Y11: =IFERROR(HLOOKUP(Y2,'Преза НЗП без НДС'!$E$2:$AL$6,5,0)*1.22,Y8) -> 441.36206 | AA11: =IFERROR(HLOOKUP(AA2,'Преза НЗП без НДС'!$E$2:$AL$6,5,0)*1.22,AA8) -> 67.187522 | AB11: =IFERROR(HLOOKUP(AB2,'Преза НЗП без НДС'!$E$2:$AL$6,5,0)*1.22,AB8) -> 107.81683 | AC11: =IFERROR(HLOOKUP(AC2,'Преза НЗП без НДС'!$E$2:$AL$6,5,0)*1.22,AC8) -> 87.282049 | AD11: =IFERROR(HLOOKUP(AD2,'Преза НЗП без НДС'!$E$2:$AL$6,5,0)*1.22,AD8) -> 830.82 | AF11: =IFERROR(HLOOKUP(AF2,'Преза НЗП без НДС'!$E$2:$AL$6,5,0)*1.22,AF8) -> 683.2 | AG11: =IFERROR(HLOOKUP(AG2,'Преза НЗП без НДС'!$E$2:$AL$6,5,0)*1.22,AG8) -> 43.916338 | AH11: =IFERROR(HLOOKUP(AH2,'Преза НЗП без НДС'!$E$2:$AL$6,5,0)*1.22,AH8) -> 384.3 | AI11: =IFERROR(HLOOKUP(AI2,'Преза НЗП без НДС'!$E$2:$AL$6,5,0)*1.22,AI8) -> 9.7562931 | AJ11: =IFERROR(HLOOKUP(AJ2,'Преза НЗП без НДС'!$E$2:$AL$6,5,0)*1.22,AJ8) -> 125.66 | AK11: =IFERROR(HLOOKUP(AK2,'Преза НЗП без НДС'!$E$2:$AL$6,5,0)*1.22,AK8) -> 56.12 | AL11: =IFERROR(HLOOKUP(AL2,'Преза НЗП без НДС'!$E$2:$AL$6,5,0)*1.22,AL8) -> 62.22 | AM11: =IFERROR(HLOOKUP(AM2,'Преза НЗП без НДС'!$E$2:$AL$6,5,0)*1.22,AM8) -> 19.900724 | ... AQ11: =IFERROR(HLOOKUP(AQ2,'Преза НЗП без НДС'!$E$2:$AL$6,5,0)*1.22,AQ8) -> 552.39558
A12: 3 | B12: Профинансировано всего, в т.ч. | C12: =D12+E12 -> 15910.857 | D12: =D14+D17+D15 -> 6493.2091 | E12: =E14+E17+E15 -> 9417.6478 | F12: =G12+H12 -> 8834.0836 | G12: =G14+G17+G15 -> 6533.8715 | H12: =H14+H17+H15 -> 2300.2122 | I12: =J12+K12+L12 -> 3581.0761 | J12: =J14+J17+J15 -> 3153.1368 | K12: =K14+K17+K15 -> 60.606299 | L12: =L14+L17+L15 -> 367.33307 | M12: =M14+M17+M15 -> 4582.2648 | N12: =N14+N17+N15 -> 1944.4813 | O12: =P12+Q12 -> 498.9676 | P12: =P14+P17+P15 -> 15.126709 | Q12: =Q14+Q17+Q15 -> 483.84089 | R12: =R14+R17+R15 -> 1069.3386 | T12: =U12+V12+W12+Z12+AD12+AE12+AH12+AI12+AJ12+AK12+AL12+AM12+AN12+AO12+AQ12 -> 5613.3571 | U12: =U14+U17+U15 -> 709.55375 | V12: =V14+V17+V15 -> 363.63203 | W12: =X12+Y12 -> 1607.6086 | X12: =X14+X17+X15 -> 1330.6896 | Y12: =Y14+Y17+Y15 -> 276.919 | Z12: =SUM(AA12:AC12) -> 230.27134 | AA12: =AA14+AA17+AA15 -> 59.434178 | AB12: =AB14+AB17+AB15 -> 93.588529 | AC12: =AC14+AC17+AC15 -> 77.248633 | AD12: =AD14+AD17+AD15 -> 738.82178 | AE12: =AF12+AG12 -> 588.8381 | AF12: =AF14+AF17+AF15 -> 553.54293 | AG12: =AG14+AG17+AG15 -> 35.295175 | AH12: =AH14+AH17+AH15 -> 356.6414 | AI12: =AI14+AI17+AI15 -> 15.857038 | AJ12: =AJ14+AJ17+AJ15 -> 103.6097 | AK12: =AK14+AK17+AK15 -> 47.657002 | AL12: =AL14+AL17+AL15 -> 55.218093 | AM12: =AM14+AM17+AM15 -> 19.850724 | ... AQ12: =AQ14+AQ17+AQ15 -> 744.97572
A13: 3.1. | B13: Выплачено по КС | C13: =D13+E13 -> 4758.8864 | D13: =D14+D15+D16 -> 4058.2561 | E13: =E14+E15+E16 -> 700.63027 | F13: =G13+H13 -> 4507.7963 | G13: =G14+G15+G16 -> 3459.5062 | H13: =H14+H15+H16 -> 1048.2901 | I13: =J13+K13+L13 -> 1897.3604 | J13: =J14+J15+J16 -> 1451.227 | K13: =K14+K15+K16 -> 70.601636 | L13: =L14+L15+L16 -> 375.53176 | M13: =M14+M15+M16 -> 1399.0691 | N13: =N14+N15+N16 -> 1050.1443 | O13: =P13+Q13 -> 459.33548 | P13: =P14+P15+P16 -> 15.126709 | Q13: =Q14+Q15+Q16 -> 444.20877 | R13: =R14+R15+R16 -> 1.491938 | T13: =U13+V13+W13+Z13+AD13+AE13+AH13+AI13+AJ13+AK13+AL13+AM13+AN13+AO13+AQ13 -> 3621.6246 | U13: =U14+U15+U16 -> 715.32881 | V13: =V14+V15+V16 -> 363.98203 | W13: =X13+Y13 -> 903.65164 | X13: =X14+X15+X16 -> 774.55115 | Y13: =Y14+Y15+Y16 -> 129.10049 | Z13: =SUM(AA13:AC13) -> 194.1157 | AA13: =AA14+AA15+AA16 -> 59.934178 | AB13: =AB14+AB15+AB16 -> 80.058398 | AC13: =AC14+AC15+AC16 -> 54.123123 | AD13: =AD14+AD15+AD16 -> 285.88779 | AE13: =AF13+AG13 -> 396.9881 | AF13: =AF14+AF15+AF16 -> 361.69293 | AG13: =AG14+AG15+AG16 -> 35.295175 | AH13: =AH14+AH15+AH16 -> 322.21292 | AI13: =AI14+AI15+AI16 -> 5.8570376 | AJ13: =AJ14+AJ15+AJ16 -> 103.80803 | AK13: =AK14+AK15+AK16 -> 47.757002 | AL13: =AL14+AL15+AL16 -> 45.518093 | AM13: =AM14+AM15+AM16 -> 13.766904 | ... AQ13: =AQ14+AQ15+AQ16 -> 191.92873
A14: 3.1.1. | B14: Прямая оплата | C14: =D14+E14 -> 1905.5392 | D14: 1602.0297 | E14: 303.50946 | F14: =G14+H14 -> 1729.775 | G14: 1613.1168 | H14: 116.65823 | I14: =J14+K14+L14 -> 539.88256 | J14: 509.00209 | K14: 0 | L14: 30.880475 | M14: 65.650185 | N14: 68.537898 | O14: =P14+Q14 -> 77.194055 | P14: 0 | Q14: 77.194055 | R14: 0 | T14: =U14+V14+W14+Z14+AD14+AE14+AH14+AI14+AJ14+AK14+AL14+AM14+AN14+AO14+AQ14 -> 3243.8326 | U14: 709.55375 | V14: 363.63203 | W14: =X14+Y14 -> 620.26717 | X14: 591.0155 | Y14: 29.251669 | Z14: =SUM(AA14:AC14) -> 192.35608 | AA14: 59.434178 | AB14: 78.798783 | AC14: 54.123123 | AD14: 206.81084 | AE14: =AF14+AG14 -> 396.8381 | AF14: 361.54293 | AG14: 35.295175 | AH14: 315.5654 | AI14: 5.8570376 | AJ14: 103.6097 | AK14: 47.657002 | AL14: 45.218093 | AM14: 13.716904 | AN14: 19.892984 | AO14: 10.928809 | AP14: 137.88477 | AQ14: 191.92873
A15: 3.1.2. | B15: По факторингу | C15: =D15+E15 -> 2598.0062 | D15: 1840.1149 | E15: 757.89126 | F15: =G15+H15 -> 2471.7056 | G15: 1651.1233 | H15: 820.58224 | I15: =J15+K15+L15 -> 1266.9538 | J15: 869.89486 | K15: 60.606299 | L15: 336.4526 | M15: 1326.1877 | N15: 974.33756 | O15: =P15+Q15 -> 364.77354 | P15: 15.126709 | Q15: 349.64683 | R15: 0 | T15: =U15+V15+W15+Z15+AD15+AE15+AH15+AI15+AJ15+AK15+AL15+AM15+AN15+AO15+AQ15 -> 243.85458 | U15: 0 | V15: 0 | W15: =X15+Y15 -> 243.85458 | X15: 208.96506 | Y15: 34.889516 | Z15: =SUM(AA15:AC15) -> 0 | AA15: 0 | AB15: 0 | AC15: 0 | AD15: 0 | AE15: =AF15+AG15 -> 0 | AF15: 0 | AG15: 0 | AH15: 0 | AI15: 0 | AJ15: 0 | AK15: 0 | AL15: 0 | AM15: 0 | AN15: 0 | AO15: 0 | AP15: 0 | AQ15: 0
A16: 3.1.3. | B16: Взаимозачет (штрафы ,межконтрактные зачеты) | C16: =D16+E16 -> 255.34103 | D16: 616.11148 | E16: -360.77045 | F16: =G16+H16 -> 306.31577 | G16: 195.26612 | H16: 111.04965 | I16: =J16+K16+L16 -> 90.524048 | J16: 72.330028 | K16: 9.9953362 | L16: 8.1986838 | M16: 7.231228 | N16: 7.2688683 | O16: =P16+Q16 -> 17.367887 | P16: 0 | Q16: 17.367887 | R16: 1.491938 | T16: =U16+V16+W16+Z16+AD16+AE16+AH16+AI16+AJ16+AK16+AL16+AM16+AN16+AO16+AQ16 -> 133.93736 | U16: 5.7750517 | V16: 0.35 | W16: =X16+Y16 -> 39.52989 | X16: -25.429412 | Y16: 64.959303 | Z16: =SUM(AA16:AC16) -> 1.759615 | AA16: 0.5 | AB16: 1.259615 | AC16: 0 | AD16: 79.076955 | AE16: =AF16+AG16 -> 0.15 | AF16: 0.15 | AG16: 0 | AH16: 6.647519 | AI16: 0 | AJ16: 0.198329 | AK16: 0.1 | AL16: 0.3 | AM16: 0.05 | AN16: 0 | AO16: 0 | AP16: 0.05 | AQ16: 0
A17: 3.2. | B17: Авансы | C17: =D17+E17 -> 11407.312 | D17: =D18+D19 -> 3051.0645 | E17: =E18+E19 -> 8356.2471 | F17: =G17+H17 -> 4632.603 | G17: =G18+G19 -> 3269.6314 | H17: =H18+H19 -> 1362.9717 | I17: =J17+K17+L17 -> 1774.2398 | J17: =J18+J19 -> 1774.2398 | K17: =K18+K19 -> 0 | L17: =L18+L19 -> 0 | M17: =M18+M19 -> 3190.4269 | N17: =N18+N19 -> 901.60586 | O17: =P17+Q17 -> 57 | P17: =P18+P19 -> 0 | Q17: =Q18+Q19 -> 57 | R17: =R18+R19 -> 1069.3386 | T17: =U17+V17+W17+Z17+AD17+AE17+AH17+AI17+AJ17+AK17+AL17+AM17+AN17+AO17+AQ17 -> 2125.6699 | U17: =U18+U19 -> 0 | V17: =V18+V19 -> 0 | W17: =X17+Y17 -> 743.48688 | X17: =X18+X19 -> 530.70906 | Y17: =Y18+Y19 -> 212.77782 | Z17: =SUM(AA17:AC17) -> 37.915256 | AA17: =AA18+AA19 -> 0 | AB17: =AB18+AB19 -> 14.789746 | AC17: =AC18+AC19 -> 23.12551 | AD17: =AD18+AD19 -> 532.01094 | AE17: =AF17+AG17 -> 192 | AF17: =AF18+AF19 -> 192 | AG17: =AG18+AG19 -> 0 | AH17: =AH18+AH19 -> 41.076 | AI17: =AI18+AI19 -> 10 | AJ17: =AJ18+AJ19 -> 0 | AK17: =AK18+AK19 -> 0 | AL17: =AL18+AL19 -> 10 | AM17: =AM18+AM19 -> 6.13382 | ... AQ17: =AQ18+AQ19 -> 553.04698
A18: 3.2.1. | B18: под БГ | C18: =D18+E18 -> 10653.034 | D18: 2926.009 | E18: 7727.0248 | F18: =G18+H18 -> 3897.6031 | G18: 2534.6314 | H18: 1362.9717 | I18: =J18+K18+L18 -> 1206.4651 | J18: 1206.4651 | K18: 0 | L18: 0 | M18: 3190.4269 | N18: 901.60586 | O18: =P18+Q18 -> 0 | P18: 0 | Q18: 0 | R18: 1069.3386 | T18: =U18+V18+W18+Z18+AD18+AE18+AH18+AI18+AJ18+AK18+AL18+AM18+AN18+AO18+AQ18 -> 631.34682 | U18: 0 | V18: 0 | W18: =X18+Y18 -> 0 | X18: 0 | Y18: 0 | Z18: =SUM(AA18:AC18) -> 0 | AA18: 0 | AB18: 0 | AC18: 0 | AD18: 382.137 | AE18: =AF18+AG18 -> 192 | AF18: 192 | AG18: 0 | AH18: 41.076 | AI18: 0 | AJ18: 0 | AK18: 0 | AL18: 10 | AM18: 6.13382 | AN18: 0 | AO18: 0 | AP18: 15 | AQ18: 0
A19: 3.2.2. | B19: под НЗП | C19: =D19+E19 -> 754.27785 | D19: 125.0555 | E19: 629.22235 | F19: =G19+H19 -> 734.99995 | G19: 734.99995 | H19: 0 | I19: =J19+K19+L19 -> 567.77469 | J19: 567.77469 | K19: 0 | L19: 0 | M19: 0 | N19: 0 | O19: =P19+Q19 -> 57 | P19: 0 | Q19: 57 | R19: 0 | T19: =U19+V19+W19+Z19+AD19+AE19+AH19+AI19+AJ19+AK19+AL19+AM19+AN19+AO19+AQ19 -> 1494.3231 | U19: 0 | V19: 0 | W19: =X19+Y19 -> 743.48688 | X19: 530.70906 | Y19: 212.77782 | Z19: =SUM(AA19:AC19) -> 37.915256 | AA19: 0 | AB19: 14.789746 | AC19: 23.12551 | AD19: 149.87394 | AE19: =AF19+AG19 -> 0 | AF19: 0 | AG19: 0 | AH19: 0 | AI19: 10 | AJ19: 0 | AK19: 0 | AL19: 0 | AM19: 0 | AN19: 0 | AO19: 0 | AP19: 0 | AQ19: 553.04698
A20: 3.3. | B20: Зачет аванса | C20: =D20+E20 -> 1319.0046 | D20: 503.13783 | E20: 815.86673 | F20: =G20+H20 -> 1536.1943 | G20: 1536.1943 | H20: -3.7252903e-15 | I20: =J20+K20+L20 -> 385.22535 | J20: 385.22535 | K20: 0 | L20: 0 | M20: 613.90751 | N20: 189.46555 | O20: =P20+Q20 -> 57 | P20: 0 | Q20: 57 | R20: 7.2086602 | T20: =U20+V20+W20+Z20+AD20+AE20+AH20+AI20+AJ20+AK20+AL20+AM20+AN20+AO20+AQ20 -> 1726.4502 | U20: 0 | V20: 0 | W20: =X20+Y20 -> 543.52047 | X20: 330.74265 | Y20: 212.77782 | Z20: =SUM(AA20:AC20) -> 37.915256 | AA20: 0 | AB20: 14.789746 | AC20: 23.12551 | AD20: 532.01094 | AE20: =AF20+AG20 -> 192 | AF20: 192 | AG20: 0 | AH20: 41.076 | AI20: 3.3268408 | AJ20: 0 | AK20: 0 | AL20: 10 | AM20: 6.13382 | AN20: 0 | AO20: 0 | AP20: 15 | AQ20: 360.46685
A21: 3.3.1. | B21: под БГ | C21: =D21+E21 -> 564.72671 | D21: 378.08233 | E21: 186.64438 | F21: =G21+H21 -> 801.19437 | G21: 801.19437 | H21: -3.7252903e-15 | I21: =J21+K21+L21 -> 100.56502 | J21: 100.56502 | K21: 0 | L21: 0 | M21: 613.90751 | N21: 189.46555 | O21: =P21+Q21 -> 0 | P21: 0 | Q21: 0 | R21: 7.2086602 | T21: =U21+V21+W21+Z21+AD21+AE21+AH21+AI21+AJ21+AK21+AL21+AM21+AN21+AO21+AQ21 -> 631.34682 | U21: 0 | V21: 0 | W21: =X21+Y21 -> 0 | X21: 0 | Y21: 0 | Z21: =SUM(AA21:AC21) -> 0 | AA21: 0 | AB21: 0 | AC21: 0 | AD21: 382.137 | AE21: =AF21+AG21 -> 192 | AF21: 192 | AG21: 0 | AH21: 41.076 | AI21: 0 | AJ21: 0 | AK21: 0 | AL21: 10 | AM21: 6.13382 | AN21: 0 | AO21: 0 | AP21: 15 | AQ21: 0
A22: 3.3.2. | B22: под НЗП | C22: =D22+E22 -> 754.27785 | D22: 125.0555 | E22: 629.22235 | F22: =G22+H22 -> 734.99995 | G22: 734.99995 | H22: 0 | I22: =J22+K22+L22 -> 284.66033 | J22: 284.66033 | K22: 0 | L22: 0 | M22: 0 | N22: 0 | O22: =P22+Q22 -> 57 | P22: 0 | Q22: 57 | R22: 0 | T22: =U22+V22+W22+Z22+AD22+AE22+AH22+AI22+AJ22+AK22+AL22+AM22+AN22+AO22+AQ22 -> 1095.1034 | U22: 0 | V22: 0 | W22: =X22+Y22 -> 543.52047 | X22: 330.74265 | Y22: 212.77782 | Z22: =SUM(AA22:AC22) -> 37.915256 | AA22: 0 | AB22: 14.789746 | AC22: 23.12551 | AD22: 149.87394 | AE22: =AF22+AG22 -> 0 | AF22: 0 | AG22: 0 | AH22: 0 | AI22: 3.3268408 | AJ22: 0 | AK22: 0 | AL22: 0 | AM22: 0 | AN22: 0 | AO22: 0 | AP22: 0 | AQ22: 360.46685
A23: 4 | B23: Задолженность всего, в т.ч. | C23: =D23+E23 -> 10083.997 | D23: =D24+D27+D28 -> 2543.6162 | E23: =E24+E27+E28 -> 7540.3804 | F23: =G23+H23 -> 2654.1061 | G23: =G24+G27+G28 -> 1478.4727 | H23: =H24+H27+H28 -> 1175.6334 | I23: =J23+K23+L23 -> 1327.2081 | J23: =J24+J27+J28 -> 1385.1207 | K23: =K24+K27+K28 -> 1.9999999e-07 | L23: =L24+L27+L28 -> -57.912595 | M23: =M24+M27+M28 -> 2576.5194 | N23: =N24+N27+N28 -> 712.14031 | O23: =P23+Q23 -> -6.8167694e-14 | P23: =P24+P27+P28 -> -6.6613381e-16 | Q23: =Q24+Q27+Q28 -> -6.750156e-14 | R23: =R24+R27+R28 -> 1049.2045 | T23: =U23+V23+W23+Z23+AD23+AE23+AH23+AI23+AJ23+AK23+AL23+AM23+AN23+AO23+AQ23 -> 221.74886 | U23: =U24+U27+U28 -> 0.03000001 | V23: =V24+V27+V28 -> -1.0000051e-08 | W23: =X23+Y23 -> 121.03952 | X23: =X24+X27+X28 -> 199.96641 | Y23: =Y24+Y27+Y28 -> -78.92689 | Z23: =SUM(AA23:AC23) -> -11.954855 | AA23: =AA24+AA27+AA28 -> -3.3522877 | AB23: =AB24+AB27+AB28 -> 9.9999884e-09 | AC23: =AC24+AC27+AC28 -> -8.6025673 | AD23: =AD24+AD27+AD28 -> -1.1368684e-13 | AE23: =AF23+AG23 -> -68.966704 | AF23: =AF24+AF27+AF28 -> -65.325428 | AG23: =AG24+AG27+AG28 -> -3.6412769 | AH23: =AH24+AH27+AH28 -> 1.7763568e-14 | AI23: =AI24+AI27+AI28 -> 6.5867314 | AJ23: =AJ24+AJ27+AJ28 -> -11.597221 | AK23: =AK24+AK27+AK28 -> -5.0281812 | AL23: =AL24+AL27+AL28 -> -2.0000009e-08 | AM23: =AM24+AM27+AM28 -> 0 | ... AQ23: =AQ24+AQ27+AQ28 -> 192.58014
A24: 4.1. | B24: Остаток незачтенного аванса | C24: =D24+E24 -> 10088.307 | D24: =D17-D20 -> 2547.9266 | E24: =E17-E20 -> 7540.3804 | F24: =G24+H24 -> 3096.4087 | G24: =G17-G20 -> 1733.437 | H24: =H17-H20 -> 1362.9717 | I24: =J24+K24+L24 -> 1389.0145 | J24: =J17-J20 -> 1389.0145 | K24: =K17-K20 -> 0 | L24: =L17-L20 -> 0 | M24: =M17-M20 -> 2576.5194 | N24: =N17-N20 -> 712.14031 | O24: =P24+Q24 -> 0 | P24: =P17-P20 -> 0 | Q24: =Q17-Q20 -> 0 | R24: =R17-R20 -> 1062.1299 | T24: =U24+V24+W24+Z24+AD24+AE24+AH24+AI24+AJ24+AK24+AL24+AM24+AN24+AO24+AQ24 -> 399.2197 | U24: =U17-U20 -> 0 | V24: =V17-V20 -> 0 | W24: =W17-W20 -> 199.96641 | X24: =X17-X20 -> 199.96641 | Y24: =Y17-Y20 -> 0 | Z24: =Z17-Z20 -> 1.0000001e-08 | AA24: =AA17-AA20 -> 0 | AB24: =AB17-AB20 -> 0 | ... AQ24: =AQ17-AQ20 -> 192.58014
A25: 4.1.1. | B25: под БГ | C25: =D25+E25 -> 10088.307 | D25: =D18-D21 -> 2547.9266 | E25: =E18-E21 -> 7540.3804 | F25: =G25+H25 -> 3096.4087 | G25: =G18-G21 -> 1733.437 | H25: =H18-H21 -> 1362.9717 | I25: =J25+K25+L25 -> 1105.9001 | J25: =J18-J21 -> 1105.9001 | K25: =K18-K21 -> 0 | L25: =L18-L21 -> 0 | M25: =M18-M21 -> 2576.5194 | N25: =N18-N21 -> 712.14031 | O25: =P25+Q25 -> 0 | P25: =P18-P21 -> 0 | Q25: =Q18-Q21 -> 0 | R25: =R18-R21 -> 1062.1299 | T25: =U25+V25+W25+Z25+AD25+AE25+AH25+AI25+AJ25+AK25+AL25+AM25+AN25+AO25+AQ25 -> 1.4690329e-09 | U25: =U18-U21 -> 0 | V25: =V18-V21 -> 0 | W25: =X25+Y25 -> 0 | X25: =X18-X21 -> 0 | Y25: =Y18-Y21 -> 0 | Z25: =SUM(AA25:AC25) -> 0 | AA25: =AA18-AA21 -> 0 | AB25: =AB18-AB21 -> 0 | AC25: =AC18-AC21 -> 0 | AD25: =AD18-AD21 -> 0 | AE25: =AF25+AG25 -> 0 | AF25: =AF18-AF21 -> 0 | AG25: =AG18-AG21 -> 0 | AH25: =AH18-AH21 -> 1.4690329e-09 | AI25: =AI18-AI21 -> 0 | AJ25: =AJ18-AJ21 -> 0 | AK25: =AK18-AK21 -> 0 | AL25: =AL18-AL21 -> 0 | AM25: =AM18-AM21 -> 0 | ... AQ25: =AQ18-AQ21 -> 0
A26: 4.1.2. | B26: под НЗП | C26: =D26+E26 -> -2.0000016e-08 | D26: =D19-D22 -> 0 | E26: =E19-E22 -> -2.0000016e-08 | F26: =G26+H26 -> 0 | G26: =G19-G22 -> 0 | H26: =H19-H22 -> 0 | I26: =J26+K26+L26 -> 283.11436 | J26: =J19-J22 -> 283.11436 | K26: =K19-K22 -> 0 | L26: =L19-L22 -> 0 | M26: =M19-M22 -> 0 | N26: =N19-N22 -> 0 | O26: =P26+Q26 -> 0 | P26: =P19-P22 -> 0 | Q26: =Q19-Q22 -> 0 | R26: =R19-R22 -> 0 | T26: =U26+V26+W26+Z26+AD26+AE26+AH26+AI26+AJ26+AK26+AL26+AM26+AN26+AO26+AQ26 -> 399.2197 | U26: =U19-U22 -> 0 | V26: =V19-V22 -> 0 | W26: =X26+Y26 -> 199.96641 | X26: =X19-X22 -> 199.96641 | Y26: =Y19-Y22 -> 0 | Z26: =SUM(AA26:AC26) -> 9.9999973e-09 | AA26: =AA19-AA22 -> 0 | AB26: =AB19-AB22 -> 0 | AC26: =AC19-AC22 -> 9.9999973e-09 | AD26: =AD19-AD22 -> 0 | AE26: =AF26+AG26 -> 0 | AF26: =AF19-AF22 -> 0 | AG26: =AG19-AG22 -> 0 | AH26: =AH19-AH22 -> 0 | AI26: =AI19-AI22 -> 6.6731592 | AJ26: =AJ19-AJ22 -> 0 | AK26: =AK19-AK22 -> 0 | AL26: =AL19-AL22 -> 0 | AM26: =AM19-AM22 -> 0 | ... AQ26: =AQ19-AQ22 -> 192.58014
A27: 4.2. | B27: Кредиторская задолженность | C27: =D27+E27 -> -4.3104042 | D27: =-(D8+D9-D13-D20+D33) -> -4.3104042 | E27: =-(E8+E9-E13-E20+E33) -> -2.8421709e-14 | F27: =G27+H27 -> -442.30261 | G27: =-(G8+G9-G13-G20+G33) -> -254.96434 | H27: =-(H8+H9-H13-H20+H33) -> -187.33827 | I27: =J27+K27+L27 -> -61.806345 | J27: =-(J8+J9-J13-J20+J33) -> -3.893751 | K27: =-(K8+K9-K13-K20+K33) -> 1.9999999e-07 | L27: =-(L8+L9-L13-L20+L33) -> -57.912595 | M27: =-(M8+M9-M13-M20+M33) -> 3.5527137e-13 | N27: =-(N8+N9-N13-N20+N33) -> 9.9475983e-14 | O27: =P27+Q27 -> -6.8167694e-14 | P27: =-(P8+P9-P13-P20+P33) -> -6.6613381e-16 | Q27: =-(Q8+Q9-Q13-Q20+Q33) -> -6.750156e-14 | R27: =-(R8+R9-R13-R20+R33) -> -12.925382 | T27: =U27+V27+W27+Z27+AD27+AE27+AH27+AI27+AJ27+AK27+AL27+AM27+AN27+AO27+AQ27 -> -177.47085 | U27: =-(U8+U9-U13-U20+U33) -> 0.03000001 | V27: =-(V8+V9-V13-V20+V33) -> -1.0000051e-08 | W27: =X27+Y27 -> -78.92689 | X27: =-(X8+X9-X13-X20+X33) -> 1.0000093e-08 | Y27: =-(Y8+Y9-Y13-Y20+Y33) -> -78.92689 | Z27: =SUM(AA27:AC27) -> -11.954855 | AA27: =-(AA8+AA9-AA13-AA20+AA33) -> -3.3522877 | AB27: =-(AB8+AB9-AB13-AB20+AB33) -> 9.9999884e-09 | AC27: =-(AC8+AC9-AC13-AC20+AC33) -> -8.6025673 | AD27: =-(AD8+AD9-AD13-AD20+AD33) -> -1.1368684e-13 | AE27: =AF27+AG27 -> -68.966704 | AF27: =-(AF8+AF9-AF13-AF20+AF33) -> -65.325428 | AG27: =-(AG8+AG9-AG13-AG20+AG33) -> -3.6412769 | AH27: =-(AH8+AH9-AH13-AH20+AH33) -> -1.4690151e-09 | AI27: =-(AI8+AI9-AI13-AI20+AI33) -> -0.08642775 | AJ27: =-(AJ8+AJ9-AJ13-AJ20+AJ33) -> -11.597221 | AK27: =-(AK8+AK9-AK13-AK20+AK33) -> -5.0281812 | AL27: =-(AL8+AL9-AL13-AL20+AL33) -> -2.0000009e-08 | AM27: =-(AM8+AM9-AM13-AM20+AM33) -> 0 | ... AQ27: =-(AQ8+AQ9-AQ13-AQ20+AQ33) -> -5.6843419e-14
A28: 4.3. | B28: Неисполненные встречные требования | C28: =D28+E28 -> 0 | D28: 0 | E28: 0 | F28: =G28+H28 -> 0 | G28: 0 | H28: 0 | I28: =J28+K28+L28 -> 0 | J28: 0 | K28: 0 | L28: 0 | M28: 0 | N28: 0 | O28: =P28+Q28 -> 0 | P28: 0 | Q28: 0 | R28: 0 | T28: =U28+V28+W28+Z28+AD28+AE28+AH28+AI28+AJ28+AK28+AL28+AM28+AN28+AO28+AQ28 -> 0 | U28: 0 | V28: 0 | W28: =X28+Y28 -> 0 | X28: 0 | Y28: 0 | Z28: =SUM(AA28:AC28) -> 0 | AA28: 0 | AB28: 0 | AC28: 0 | AD28: 0 | AE28: =AF28+AG28 -> 0 | AF28: 0 | AG28: 0 | AH28: 0 | AI28: 0 | AJ28: 0 | AK28: 0 | AL28: 0 | AM28: 0 | AN28: 0 | AO28: 0 | AP28: 0 | AQ28: 0
A29: 5 | B29: Обеспечение | C29: =D29+E29 -> -11316.966 | D29: =SUM(D30:D32) -> -3400.1166 | E29: =SUM(E30:E32) -> -7916.8498 | F29: =G29+H29 -> -2436.9754 | G29: =SUM(G30:G32) -> -819.75998 | H29: =SUM(H30:H32) -> -1617.2155 | I29: =J29+K29+L29 -> -1822.3149 | J29: =SUM(J30:J32) -> -1731.8345 | K29: =SUM(K30:K32) -> -3.7158752 | L29: =SUM(L30:L32) -> -86.764513 | M29: =SUM(M30:M32) -> -3422.3861 | N29: =SUM(N30:N32) -> -1108.9749 | O29: =P29+Q29 -> -164.67367 | P29: =SUM(P30:P32) -> -1.6807455 | Q29: =SUM(Q30:Q32) -> -162.99292 | R29: =SUM(R30:R32) -> -1132.9741 | T29: =U29+V29+W29+Z29+AD29+AE29+AH29+AI29+AJ29+AK29+AL29+AM29+AN29+AO29+AQ29 -> -485.04075 | U29: =SUM(U30:U32) -> -195.76916 | V29: =SUM(V30:V32) -> -44.944529 | W29: =X29+Y29 -> -80.321 | X29: =SUM(X30:X32) -> -58.173358 | Y29: =SUM(Y30:Y32) -> -22.147642 | Z29: =SUM(AA29:AC29) -> -17.419438 | AA29: =SUM(AA30:AA32) -> -3.7913025 | AB29: =SUM(AB30:AB32) -> -12.483456 | AC29: =SUM(AC30:AC32) -> -1.1446788 | AD29: =SUM(AD30:AD32) -> -10.337011 | AE29: =AF29+AG29 -> -73.628981 | AF29: =SUM(AF30:AF32) -> -68.779817 | AG29: =SUM(AG30:AG32) -> -4.8491639 | AH29: =SUM(AH30:AH32) -> -39.793393 | AI29: =SUM(AI30:AI32) -> -0.48598696 | AJ29: =SUM(AJ30:AJ32) -> -10.028671 | AK29: =SUM(AK30:AK32) -> -3.4065035 | AL29: =SUM(AL30:AL32) -> -6.5952611 | AM29: =SUM(AM30:AM32) -> 0 | ... AQ29: =SUM(AQ30:AQ32) -> 0
A30: 5.1. | B30: Банковская гарантия | C30: =D30+E30 -> -10404.742 | D30: -2823.0877 | E30: -7581.6541 | F30: =G30+H30 -> -1362.9717 | G30: 0 | H30: -1362.9717 | I30: =J30+K30+L30 -> -1204.0264 | J30: -1204.0264 | K30: 0 | L30: 0 | M30: -2797.9742 | N30: -901.60586 | O30: =P30+Q30 -> 0 | P30: 0 | Q30: 0 | R30: -1069.3386 | T30: =U30+V30+W30+Z30+AD30+AE30+AH30+AI30+AJ30+AK30+AL30+AM30+AN30+AO30+AQ30 -> -19.153776 | U30: 0 | V30: 0 | W30: =X30+Y30 -> 0 | X30: 0 | Y30: 0 | Z30: =SUM(AA30:AC30) -> 0 | AA30: 0 | AB30: 0 | AC30: 0 | AD30: 0 | AE30: =AF30+AG30 -> 0 | AF30: 0 | AG30: 0 | AH30: -19.153776 | AI30: 0 | AJ30: 0 | AK30: 0 | AL30: 0 | AM30: 0 | AN30: 0 | AO30: 0 | AP30: 0 | AQ30: 0
A31: 5.2. | B31: НЗП * 0,8 (коэф.конс) | C31: =D31+E31 -> -578.27834 | D31: =-D10*0.95*0.8 -> -327.63563 | E31: =-E10*0.95*0.8 -> -250.64271 | F31: =G31+H31 -> -785.72696 | G31: =-G10*0.95*0.8 -> -591.95633 | H31: =-H10*0.95*0.8 -> -193.77063 | I31: =J31+K31+L31 -> -470.22464 | J31: =-J10*0.95*0.8 -> -409.44323 | K31: =-K10*0.95*0.8 -> 0 | L31: =-L10*0.95*0.8 -> -60.781409 | M31: =-M10*0.95*0.8 -> -492.78163 | N31: =-N10*0.95*0.8 -> -135.02012 | O31: =P31+Q31 -> -130.07237 | P31: =-P10*0.95*0.8 -> 0 | Q31: =-Q10*0.95*0.8 -> -130.07237 | R31: =-R10*0.95*0.8 -> -58.171036 | T31: =U31+V31+W31+Z31+AD31+AE31+AH31+AI31+AJ31+AK31+AL31+AM31+AN31+AO31+AQ31 -> -128.09919 | U31: =-U10*0.95*0.8 -> -107.66172 | V31: =-V10*0.95*0.8 -> -4.0962577 | W31: =X31+Y31 -> 0 | X31: =-X10*0.95*0.8 -> 0 | Y31: =-Y10*0.95*0.8 -> 0 | Z31: =SUM(AA31:AC31) -> -3.3484007 | AA31: =-AA10*0.95*0.8 -> -0.41706404 | AB31: =-AB10*0.95*0.8 -> -1.8438918 | AC31: =-AC10*0.95*0.8 -> -1.0874449 | AD31: =-AD10*0.95*0.8 -> -9.8201604 | AE31: =AF31+AG31 -> -0.4967469 | AF31: =-AF10*0.95*0.8 -> 0 | AG31: =-AG10*0.95*0.8 -> -0.4967469 | AH31: =-AH10*0.95*0.8 -> -1.4115482 | AI31: =-AI10*0.95*0.8 -> 0 | AJ31: =-AJ10*0.95*0.8 -> -0.85909512 | AK31: =-AK10*0.95*0.8 -> 0 | AL31: =-AL10*0.95*0.8 -> -0.40525487 | AM31: =-AM10*0.95*0.8 -> 0 | ... AQ31: =-AQ10*0.95*0.8 -> 0
A32: 5.3. | B32: ГУ | C32: =D32+E32 -> -333.94632 | D32: =SUM(D33:D34) -> -249.39328 | E32: =SUM(E33:E34) -> -84.553043 | F32: =G32+H32 -> -288.27678 | G32: =SUM(G33:G34) -> -227.80365 | H32: =SUM(H33:H34) -> -60.473129 | I32: =J32+K32+L32 -> -148.06383 | J32: =SUM(J33:J34) -> -118.36485 | K32: =SUM(K33:K34) -> -3.7158752 | L32: =SUM(L33:L34) -> -25.983104 | M32: =SUM(M33:M34) -> -131.63022 | N32: =SUM(N33:N34) -> -72.348947 | O32: =P32+Q32 -> -34.601297 | P32: =SUM(P33:P34) -> -1.6807455 | Q32: =SUM(Q33:Q34) -> -32.920551 | R32: =SUM(R33:R34) -> -5.4645202 | T32: =U32+V32+W32+Z32+AD32+AE32+AH32+AI32+AJ32+AK32+AL32+AM32+AN32+AO32+AQ32 -> -337.78779 | U32: =SUM(U33:U34) -> -88.107441 | V32: =SUM(V33:V34) -> -40.848271 | W32: =X32+Y32 -> -80.321 | X32: =SUM(X33:X34) -> -58.173358 | Y32: =SUM(Y33:Y34) -> -22.147642 | Z32: =SUM(AA32:AC32) -> -14.071037 | AA32: =SUM(AA33:AA34) -> -3.3742384 | AB32: =SUM(AB33:AB34) -> -10.639565 | AC32: =SUM(AC33:AC34) -> -0.05723394 | AD32: =SUM(AD33:AD34) -> -0.51685055 | AE32: =AF32+AG32 -> -73.132234 | AF32: =SUM(AF33:AF34) -> -68.779817 | AG32: =SUM(AG33:AG34) -> -4.352417 | AH32: =SUM(AH33:AH34) -> -19.228068 | AI32: =SUM(AI33:AI34) -> -0.48598696 | AJ32: =SUM(AJ33:AJ34) -> -9.1695756 | AK32: =SUM(AK33:AK34) -> -3.4065035 | AL32: =SUM(AL33:AL34) -> -6.1900062 | AM32: =SUM(AM33:AM34) -> 0 | ... AQ32: =SUM(AQ33:AQ34) -> 0
A33: 5.3.1. | B33: ГУ с принятых работ | C33: =D33+E33 -> -303.51062 | D33: -232.1493 | E33: -71.361322 | F33: =G33+H33 -> -246.92273 | G33: -196.64806 | H33: -50.274675 | I33: =J33+K33+L33 -> -123.31517 | J33: -96.815209 | K33: -3.7158752 | L33: -22.784082 | M33: -105.69435 | N33: -65.242625 | O33: =P33+Q33 -> -27.755382 | P33: -1.6807455 | Q33: -26.074637 | R33: -2.4028867 | T33: =U33+V33+W33+Z33+AD33+AE33+AH33+AI33+AJ33+AK33+AL33+AM33+AN33+AO33+AQ33 -> -331.04573 | U33: -82.441034 | V33: -40.632679 | W33: =X33+Y33 -> -80.321 | X33: -58.173358 | Y33: -22.147642 | Z33: =SUM(AA33:AC33) -> -13.894805 | AA33: -3.3522877 | AB33: -10.542518 | AC33: 0 | AD33: 0 | AE33: =AF33+AG33 -> -73.10609 | AF33: -68.779817 | AG33: -4.3262724 | AH33: -19.153776 | AI33: -0.48598696 | AJ33: -9.1243601 | AK33: -3.4065035 | AL33: -6.168677 | AM33: 0 | AN33: -1.0965027 | AO33: -1.2143121 | AP33: -18.938142 | AQ33: 0
A34: 5.3.2. | B34: ГУ с НЗП | C34: =D34+E34 -> -30.435702 | D34: =-D10*0.05*0.8 -> -17.243981 | E34: =-E10*0.05*0.8 -> -13.191721 | F34: =G34+H34 -> -41.35405 | G34: =-G10*0.05*0.8 -> -31.155596 | H34: =-H10*0.05*0.8 -> -10.198454 | I34: =J34+K34+L34 -> -24.748665 | J34: =-J10*0.05*0.8 -> -21.549644 | K34: =-K10*0.05*0.8 -> 0 | L34: =-L10*0.05*0.8 -> -3.1990215 | M34: =-M10*0.05*0.8 -> -25.935875 | N34: =-N10*0.05*0.8 -> -7.1063223 | O34: =P34+Q34 -> -6.8459144 | P34: =-P10*0.05*0.8 -> 0 | Q34: =-Q10*0.05*0.8 -> -6.8459144 | R34: =-R10*0.05*0.8 -> -3.0616335 | T34: =U34+V34+W34+Z34+AD34+AE34+AH34+AI34+AJ34+AK34+AL34+AM34+AN34+AO34+AQ34 -> -6.7420624 | U34: =-U10*0.05*0.8 -> -5.6664064 | V34: =-V10*0.05*0.8 -> -0.21559251 | W34: =X34+Y34 -> 0 | X34: =-X10*0.05*0.8 -> 0 | Y34: =-Y10*0.05*0.8 -> 0 | Z34: =SUM(AA34:AC34) -> -0.17623161 | AA34: =-AA10*0.05*0.8 -> -0.021950739 | AB34: =-AB10*0.05*0.8 -> -0.097046936 | AC34: =-AC10*0.05*0.8 -> -0.05723394 | AD34: =-AD10*0.05*0.8 -> -0.51685055 | AE34: =AF34+AG34 -> -0.026144574 | AF34: =-AF10*0.05*0.8 -> 0 | AG34: =-AG10*0.05*0.8 -> -0.026144574 | AH34: =-AH10*0.05*0.8 -> -0.07429201 | AI34: =-AI10*0.05*0.8 -> 0 | AJ34: =-AJ10*0.05*0.8 -> -0.045215533 | AK34: =-AK10*0.05*0.8 -> 0 | AL34: =-AL10*0.05*0.8 -> -0.021329204 | AM34: =-AM10*0.05*0.8 -> 0 | ... AQ34: =-AQ10*0.05*0.8 -> 0
A35: 6 | B35: Баланс взаиморасчетов (без учета ГУ) | C35: =D35+E35 -> -899.02345 | D35: =SUM(D36:D38) -> -607.10706 | E35: =SUM(E36:E38) -> -291.91639 | F35: =G35+H35 -> 505.40746 | G35: =SUM(G36:G38) -> 886.51637 | H35: =SUM(H36:H38) -> -381.10891 | I35: =J35+K35+L35 -> -347.04295 | J35: =SUM(J36:J38) -> -228.34895 | K35: =SUM(K36:K38) -> 1.9999999e-07 | L35: =SUM(L36:L38) -> -118.694 | M35: =SUM(M36:M38) -> -714.23642 | N35: =SUM(N36:N38) -> -324.48568 | O35: =P35+Q35 -> -130.07237 | P35: =SUM(P36:P38) -> -6.6613381e-16 | Q35: =SUM(Q36:Q38) -> -130.07237 | R35: =SUM(R36:R38) -> -78.305079 | T35: =U35+V35+W35+Z35+AD35+AE35+AH35+AI35+AJ35+AK35+AL35+AM35+AN35+AO35+AQ35 -> 74.495896 | U35: =SUM(U36:U38) -> -107.63172 | V35: =SUM(V36:V38) -> -4.0962577 | W35: =X35+Y35 -> 121.03952 | X35: =SUM(X36:X38) -> 199.96641 | Y35: =SUM(Y36:Y38) -> -78.92689 | Z35: =SUM(AA35:AC35) -> -15.303256 | AA35: =SUM(AA36:AA38) -> -3.7693517 | AB35: =SUM(AB36:AB38) -> -1.8438918 | AC35: =SUM(AC36:AC38) -> -9.6900122 | AD35: =SUM(AD36:AD38) -> -9.8201605 | AE35: =AF35+AG35 -> -69.463451 | AF35: =SUM(AF36:AF38) -> -65.325428 | AG35: =SUM(AG36:AG38) -> -4.1380238 | AH35: =SUM(AH36:AH38) -> -20.565324 | AI35: =SUM(AI36:AI38) -> 6.5867314 | AJ35: =SUM(AJ36:AJ38) -> -12.456316 | AK35: =SUM(AK36:AK38) -> -5.0281812 | AL35: =SUM(AL36:AL38) -> -0.40525489 | AM35: =SUM(AM36:AM38) -> 0 | ... AQ35: =SUM(AQ36:AQ38) -> 192.58014
A36: 6.1. | B36: по БГ | C36: =D36+E36 -> -316.4347 | D36: =D30+D25 -> -275.16102 | E36: =E30+E25 -> -41.273678 | F36: =G36+H36 -> 1733.437 | G36: =G30+G25 -> 1733.437 | H36: =H30+H25 -> -1.7000002e-07 | I36: =J36+K36+L36 -> -98.126328 | J36: =J30+J25 -> -98.126328 | K36: =K30+K25 -> 0 | L36: =L30+L25 -> 0 | M36: =M30+M25 -> -221.45478 | N36: =N30+N25 -> -189.46555 | O36: =P36+Q36 -> 0 | P36: =P30+P25 -> 0 | Q36: =Q30+Q25 -> 0 | R36: =R30+R25 -> -7.2086602 | T36: =U36+V36+W36+Z36+AD36+AE36+AH36+AI36+AJ36+AK36+AL36+AM36+AN36+AO36+AQ36 -> -19.153776 | U36: =U30+U25 -> 0 | V36: =V30+V25 -> 0 | W36: =X36+Y36 -> 0 | X36: =X30+X25 -> 0 | Y36: =Y30+Y25 -> 0 | Z36: =SUM(AA36:AC36) -> 0 | AA36: =AA30+AA25 -> 0 | AB36: =AB30+AB25 -> 0 | AC36: =AC30+AC25 -> 0 | AD36: =AD30+AD25 -> 0 | AE36: =AF36+AG36 -> 0 | AF36: =AF30+AF25 -> 0 | AG36: =AG30+AG25 -> 0 | AH36: =AH30+AH25 -> -19.153776 | AI36: =AI30+AI25 -> 0 | AJ36: =AJ30+AJ25 -> 0 | AK36: =AK30+AK25 -> 0 | AL36: =AL30+AL25 -> 0 | AM36: =AM30+AM25 -> 0 | ... AQ36: =AQ30+AQ25 -> 0
A37: 6.2. | B37: по НЗП | C37: =D37+E37 -> -578.27834 | D37: =D31+D26 -> -327.63563 | E37: =E31+E26 -> -250.64271 | F37: =G37+H37 -> -785.72696 | G37: =G31+G26 -> -591.95633 | H37: =H31+H26 -> -193.77063 | I37: =J37+K37+L37 -> -187.11028 | J37: =J31+J26 -> -126.32887 | K37: =K31+K26 -> 0 | L37: =L31+L26 -> -60.781409 | M37: =M31+M26 -> -492.78163 | N37: =N31+N26 -> -135.02012 | O37: =P37+Q37 -> -130.07237 | P37: =P31+P26 -> 0 | Q37: =Q31+Q26 -> -130.07237 | R37: =R31+R26 -> -58.171036 | T37: =U37+V37+W37+Z37+AD37+AE37+AH37+AI37+AJ37+AK37+AL37+AM37+AN37+AO37+AQ37 -> 271.12052 | U37: =U31+U26 -> -107.66172 | V37: =V31+V26 -> -4.0962577 | W37: =X37+Y37 -> 199.96641 | X37: =X31+X26 -> 199.96641 | Y37: =Y31+Y26 -> 0 | Z37: =SUM(AA37:AC37) -> -3.3484007 | AA37: =AA31+AA26 -> -0.41706404 | AB37: =AB31+AB26 -> -1.8438918 | AC37: =AC31+AC26 -> -1.0874449 | AD37: =AD31+AD26 -> -9.8201604 | AE37: =AF37+AG37 -> -0.4967469 | AF37: =AF31+AF26 -> 0 | AG37: =AG31+AG26 -> -0.4967469 | AH37: =AH31+AH26 -> -1.4115482 | AI37: =AI31+AI26 -> 6.6731592 | AJ37: =AJ31+AJ26 -> -0.85909512 | AK37: =AK31+AK26 -> 0 | AL37: =AL31+AL26 -> -0.40525487 | AM37: =AM31+AM26 -> 0 | ... AQ37: =AQ31+AQ26 -> 192.58014
A38: 6.3. | B38: по ДЗ/КЗ | C38: =D38+E38 -> -4.3104042 | D38: =D27+D28 -> -4.3104042 | E38: =E27+E28 -> -2.8421709e-14 | F38: =G38+H38 -> -442.30261 | G38: =G27+G28 -> -254.96434 | H38: =H27+H28 -> -187.33827 | I38: =J38+K38+L38 -> -61.806345 | J38: =J27+J28 -> -3.893751 | K38: =K27+K28 -> 1.9999999e-07 | L38: =L27+L28 -> -57.912595 | M38: =M27+M28 -> 3.5527137e-13 | N38: =N27+N28 -> 9.9475983e-14 | O38: =P38+Q38 -> -6.8167694e-14 | P38: =P27+P28 -> -6.6613381e-16 | Q38: =Q27+Q28 -> -6.750156e-14 | R38: =R27+R28 -> -12.925382 | T38: =U38+V38+W38+Z38+AD38+AE38+AH38+AI38+AJ38+AK38+AL38+AM38+AN38+AO38+AQ38 -> -177.47085 | U38: =U27+U28 -> 0.03000001 | V38: =V27+V28 -> -1.0000051e-08 | W38: =X38+Y38 -> -78.92689 | X38: =X27+X28 -> 1.0000093e-08 | Y38: =Y27+Y28 -> -78.92689 | Z38: =SUM(AA38:AC38) -> -11.954855 | AA38: =AA27+AA28 -> -3.3522877 | AB38: =AB27+AB28 -> 9.9999884e-09 | AC38: =AC27+AC28 -> -8.6025673 | AD38: =AD27+AD28 -> -1.1368684e-13 | AE38: =AF38+AG38 -> -68.966704 | AF38: =AF27+AF28 -> -65.325428 | AG38: =AG27+AG28 -> -3.6412769 | AH38: =AH27+AH28 -> -1.4690151e-09 | AI38: =AI27+AI28 -> -0.08642775 | AJ38: =AJ27+AJ28 -> -11.597221 | AK38: =AK27+AK28 -> -5.0281812 | AL38: =AL27+AL28 -> -2.0000009e-08 | AM38: =AM27+AM28 -> 0 | ... AQ38: =AQ27+AQ28 -> -5.6843419e-14

Sheet Баланс ФЭК (валюта) с НДС
A1: № п/п | B1: НАИМЕПодрядчик 4НИЕ | C1: ВСЕГО млн USD с НДС | D1: Подрядчик 1 | E1: Подрядчик 1 | F1: Подрядчик 1 | G1: Подрядчик 2 | H1: Подрядчик 2 | I1: Подрядчик 3 | J1: Подрядчик 3 | K1: Подрядчик 3 | L1: Подрядчик 17 | M1: млн в валюте контракта с НДС | N1: дата актуальности НЗП | O1: ='Преза НЗП без НДС'!AO1 -> 46280
B2: договор | E2: Дог.9756 | F2: Дог.10675 | G2: Дог.10221 | H2: Дог.11996 | I2: Дог.10321 | J2: Дог.10321-5 | K2: Дог.11980 | L2: Дог.11820
B3: вид работ/проект | E3: Монолит | F3: ММР ЭМР | G3: монолит ПС и ОЗХ | H3: ММР ПС | I3: ГП мПЭ | J3: Резервуары готовой продукци | K3: Резервуары готовой продукци | L3: Монтаж МК
B4: курс | E4: 89.79 | F4: 80 | G4: 91.5 | H4: 80 | I4: 80 | J4: 80 | K4: 85 | L4: 80
E5: =E8*E4 -> 4798.0267 | F5: =F8*F4 -> 1575.2285 | G5: =G8*G4 -> 5445.8662 | H5: =H8*H4 -> 1288.7944 | I5: =I8*I4 -> 1925.8669 | J5: =J8*J4 -> 73.665158 | K5: =K8*K4 -> 455.65139 | L5: =L8*L4 -> 9.6150544
A6: 1 | B6: Стоимость работ по контракту | C6: =SUM(D6,G6:L6) -> 621.22711 | D6: =E6+F6 -> 286.00138 | E6: 78.017844 | F6: 207.98354 | G6: 93.314171 | H6: 127.31241 | I6: 92.028887 | J6: 1.2616203 | K6: 20.244132 | L6: 1.0645068
A7: 2 | B7: Выполнение всего, в том числе | C7: =SUM(D7,G7:L7) -> 207.52722 | D7: =E7+F7 -> 82.050058 | E7: =E8+E9 -> 58.23729 | F7: =F8+F9 -> 23.812769 | G7: =G8+G9 -> 68.030122 | H7: =H8+H9 -> 19.296947 | I7: =I8+I9 -> 30.8076 | J7: =J8+J9 -> 0.92081448 | K7: =K8+K9 -> 6.3014933 | L7: =L8+L9 -> 0.12018818
A8: 2.1. | B8: Принято (КС-2) | C8: =SUM(D8,G8:L8) -> 179.22899 | D8: =E8+F8 -> 73.126448 | E8: 53.436092 | F8: 19.690356 | G8: 59.517664 | H8: 16.10993 | I8: 24.073337 | J8: 0.92081448 | K8: 5.3606046 | L8: 0.12018818
A9: 2.2. | B9: НЗП | C9: =SUM(D9,G9:L9) -> 28.298238 | D9: =E9+F9 -> 8.9236104 | E9: ='БАЛАНС РУКОВОДСТВУ руб. с НДС'!D10/'БАЛАНС РУКОВОДСТВУ руб. с НДС'!D4 -> 4.8011975 | F9: ='БАЛАНС РУКОВОДСТВУ руб. с НДС'!E10/'БАЛАНС РУКОВОДСТВУ руб. с НДС'!E4 -> 4.1224129 | G9: ='БАЛАНС РУКОВОДСТВУ руб. с НДС'!G10/'БАЛАНС РУКОВОДСТВУ руб. с НДС'!G4 -> 8.5124579 | H9: ='БАЛАНС РУКОВОДСТВУ руб. с НДС'!H10/'БАЛАНС РУКОВОДСТВУ руб. с НДС'!H4 -> 3.187017 | I9: ='БАЛАНС РУКОВОДСТВУ руб. с НДС'!J10/'БАЛАНС РУКОВОДСТВУ руб. с НДС'!J4 -> 6.7342636 | J9: ='БАЛАНС РУКОВОДСТВУ руб. с НДС'!K10/'БАЛАНС РУКОВОДСТВУ руб. с НДС'!K4 -> 0 | K9: ='БАЛАНС РУКОВОДСТВУ руб. с НДС'!L10/'БАЛАНС РУКОВОДСТВУ руб. с НДС'!L4 -> 0.94088868 | L9: ='БАЛАНС РУКОВОДСТВУ руб. с НДС'!AI10/'БАЛАНС РУКОВОДСТВУ руб. с НДС'!AI4 -> 0
A10: 3 | B10: Профинансировано всего, в т.ч. | C10: =SUM(D10,G10:L10) -> 335.19374 | D10: =E10+F10 -> 188.55919 | E10: =E12+E13+E15 -> 72.315504 | F10: =F12+F13+F15 -> 116.24369 | G10: =G12+G13+G15 -> 71.408431 | H10: =H12+H13+H15 -> 30.792785 | I10: =I12+I13+I15 -> 39.170381 | J10: =J12+J13+J15 -> 0.74983206 | K10: =K12+K13+K15 -> 4.3155605 | L10: =L12+L13+L15 -> 0.19756065
A11: 3.1. | B11: Выплачено по КС | C11: =SUM(D11,G11:L11) -> 128.8741 | D11: =E11+F11 -> 54.620721 | E11: =E12+E13+E14 -> 45.199122 | F11: =F12+F13+F14 -> 9.4215994 | G11: =G12+G13+G14 -> 37.793 | H11: =H12+H13+H14 -> 13.13815 | I11: =I12+I13+I14 -> 17.963642 | J11: =J12+J13+J14 -> 0.87477376 | K11: =K12+K13+K14 -> 4.4112498 | L11: =L12+L13+L14 -> 0.07256065
A12: 3.1.1. | B12: Прямая оплата | C12: =SUM(D12,G12:L12) -> 47.553482 | D12: =E12+F12 -> 21.635829 | E12: 17.841961 | F12: 3.7938682 | G12: 17.629691 | H12: 1.5714197 | I12: 6.280681 | J12: 0 | K12: 0.36329971 | L12: 0.07256065
A13: 3.1.2. | B13: По факторингу | C13: =SUM(D13,G13:L13) -> 73.621363 | D13: =E13+F13 -> 29.95093 | E13: 20.49354 | F13: 9.4573905 | G13: 18.045064 | H13: 10.124503 | I13: 10.798773 | J13: 0.74983206 | K13: 3.9522608 | L13: 0
A14: 3.1.3. | B14: Взаимозачет (штрафы, проживание, межконтрактные зачеты) | C14: =SUM(D14,G14:L14) -> 7.6992528 | D14: =E14+F14 -> 3.0339618 | E14: 6.8636211 | F14: -3.8296593 | G14: 2.1182448 | H14: 1.4422273 | I14: 0.88418792 | J14: 0.1249417 | K14: 0.095689288 | L14: 0
A15: 3.2. | B15: Авансы | C15: =SUM(D15,G15:L15) -> 214.01889 | D15: =E15+F15 -> 136.97243 | E15: =E16+E17 -> 33.980003 | F15: =F16+F17 -> 102.99243 | G15: =G16+G17 -> 35.733676 | H15: =H16+H17 -> 19.096862 | I15: =I16+I17 -> 22.090927 | J15: =J16+J17 -> 0 | K15: =K16+K17 -> 0 | L15: =L16+L17 -> 0.125
A16: 3.2.1. | B16: Авансы под БГ | C16: =SUM(D16,G16:L16) -> 190.34031 | D16: =E16+F16 -> 128.51714 | E16: 32.587248 | F16: 95.929897 | G16: 27.70089 | H16: 19.096862 | I16: 15.025417 | J16: 0 | K16: 0 | L16: 0
A17: 3.2.2. | B17: Авансы ОБС / НЗП | C17: =SUM(D17,G17:L17) -> 23.678582 | D17: =E17+F17 -> 8.4552852 | E17: 1.3927553 | F17: 7.0625299 | G17: 8.0327864 | H17: 0 | I17: 7.0655106 | J17: 0 | K17: 0 | L17: 0.125
A18: 3.3. | B18: Зачет аванса | C18: =SUM(D18,G18:L18) -> 36.67217 | D18: =E18+F18 -> 14.984466 | E18: 5.6034952 | F18: 9.3809712 | G18: 16.789009 | H18: 0 | I18: 4.8571091 | J18: 0 | K18: 0 | L18: 0.04158551
A19: 3.3.1. | B19: Зачет под БГ | C19: =SUM(D19,G19:L19) -> 16.542467 | D19: =E19+F19 -> 6.5291812 | E19: 4.2107399 | F19: 2.3184413 | G19: 8.7562226 | H19: 0 | I19: 1.2570628 | J19: 0 | K19: 0 | L19: 0
A20: 3.3.2. | B20: Зачет под ОБС / НЗП | C20: =SUM(D20,G20:L20) -> 20.129703 | D20: =E20+F20 -> 8.4552852 | E20: 1.3927553 | F20: 7.0625299 | G20: 8.0327864 | H20: 0 | I20: 3.6000463 | J20: 0 | K20: 0 | L20: 0.04158551
A21: 4 | B21: Задолженность всего, в т.ч. | C21: =SUM(D21,G21:L21) -> 171.4405 | D21: =E21+F21 -> 121.93996 | E21: =E22+E25+E26 -> 28.328502 | F21: =F22+F25+F26 -> 93.611455 | G21: =G22+G25+G26 -> 16.158172 | H21: =H22+H25+H26 -> 16.755134 | I21: =I22+I25+I26 -> 17.185146 | J21: =J22+J25+J26 -> 2.4999998e-09 | K21: =K22+K25+K26 -> -0.68132464 | L21: =L22+L25+L26 -> 0.08341449
A22: 4.1. | B22: Остаток незачтенного аванса | C22: =SUM(D22,G22:L22) -> 177.34672 | D22: =E22+F22 -> 121.98796 | E22: =E15-E18 -> 28.376508 | F22: =F15-F18 -> 93.611455 | G22: =G15-G18 -> 18.944667 | H22: =H15-H18 -> 19.096862 | I22: =I15-I18 -> 17.233818 | J22: =J15-J18 -> 0 | K22: =K15-K18 -> 0 | L22: =L15-L18 -> 0.08341449
A23: 4.1.1. | B23: НЗА под БГ | C23: =SUM(D23,G23:L23) -> 173.79785 | D23: =E23+F23 -> 121.98796 | E23: =E16-E19 -> 28.376508 | F23: =F16-F19 -> 93.611455 | G23: =G16-G19 -> 18.944667 | H23: =H16-H19 -> 19.096862 | I23: =I16-I19 -> 13.768354 | J23: =J16-J19 -> 0 | K23: =K16-K19 -> 0 | L23: =L16-L19 -> 0
A24: 4.1.2. | B24: НЗА под ОБС / НЗП | C24: =SUM(D24,G24:L24) -> 3.5488788 | D24: =E24+F24 -> 0 | E24: =E17-E20 -> 0 | F24: =F17-F20 -> 0 | G24: =G17-G20 -> 0 | H24: =H17-H20 -> 0 | I24: =I17-I20 -> 3.4654643 | J24: =J17-J20 -> 0 | K24: =K17-K20 -> 0 | L24: =L17-L20 -> 0.08341449
A25: 4.2. | B25: Кредиторская задолженность | C25: =SUM(D25,G25:L25) -> -5.9062259 | D25: =E25+F25 -> -0.048005392 | E25: =-(E8-E11-E18+E31) -> -0.048005392 | F25: =-(F8-F11-F18+F31) -> 2.220446e-16 | G25: =-(G8-G11-G18+G31) -> -2.7864955 | H25: =-(H8-H11-H18+H31) -> -2.3417284 | I25: =-(I8-I11-I18+I31) -> -0.048671887 | J25: =-(J8-J11-J18+J31) -> 2.4999998e-09 | K25: =-(K8-K11-K18+K31) -> -0.68132464 | L25: =-(L8-L11-L18+L31) -> -1.7347235e-18
A26: 4.3. | B26: Неисполненные встречные требования | C26: =SUM(D26,G26:L26) -> 0 | D26: =E26+F26 -> 0 | E26: 0 | F26: 0 | G26: 0 | H26: 0 | I26: 0 | J26: 0 | K26: 0 | L26: 0
A27: 5 | B27: Обеспечение | C27: =SUM(D27,G27:L27) -> -191.02296 | D27: =E27+F27 -> -136.82382 | E27: =SUM(E28:E30) -> -37.86743 | F27: =SUM(F28:F30) -> -98.956392 | G27: =SUM(G28:G30) -> -8.9591255 | H27: =SUM(H28:H30) -> -22.276527 | I27: =SUM(I28:I30) -> -21.89066 | J27: =SUM(J28:J30) -> -0.04604072 | K27: =SUM(K28:K30) -> -1.0207412 | L27: =SUM(L28:L30) -> -0.00604202
A28: 5.1. | B28: Банковская гарантия | C28: =SUM(D28,G28:L28) -> -160.60788 | D28: =E28+F28 -> -126.21168 | E28: -31.441003 | F28: -94.770676 | G28: 0 | H28: -19.096862 | I28: -15.299336 | J28: 0 | K28: 0 | L28: 0
A29: 5.2. | B29: НЗП * 0,8 (коэф.конс) | C29: =SUM(D29,G29:L29) -> -21.506661 | D29: =E29+F29 -> -6.7819439 | E29: =-E9*0.95*0.8 -> -3.6489101 | F29: =-F9*0.95*0.8 -> -3.1330338 | G29: =-G9*0.95*0.8 -> -6.469468 | H29: =-H9*0.95*0.8 -> -2.4221329 | I29: =-I9*0.95*0.8 -> -5.1180404 | J29: =-J9*0.95*0.8 -> 0 | K29: =-K9*0.95*0.8 -> -0.7150754 | L29: =-L9*0.95*0.8 -> 0
A30: 5.3. | B30: ГУ | C30: =SUM(D30,G30:L30) -> -8.9084212 | D30: =E30+F30 -> -3.8301991 | E30: =SUM(E31:E32) -> -2.7775173 | F30: =SUM(F31:F32) -> -1.0526818 | G30: =SUM(G31:G32) -> -2.4896574 | H30: =SUM(H31:H32) -> -0.75753187 | I30: =SUM(I31:I32) -> -1.4732843 | J30: =SUM(J31:J32) -> -0.04604072 | K30: =SUM(K31:K32) -> -0.30566577 | L30: =SUM(L31:L32) -> -0.00604202
A31: 5.3.1. | B31: ГУ с принятых работ | C31: =SUM(D31,G31:L31) -> -7.7764917 | D31: =E31+F31 -> -3.4732547 | E31: -2.5854694 | F31: -0.88778533 | G31: -2.1491591 | H31: -0.63005119 | I31: -1.2039138 | J31: -0.04604072 | K31: -0.26803022 | L31: -0.00604202
A32: 5.3.2. | B32: ГУ с НЗП | C32: =SUM(D32,G32:L32) -> -1.1319295 | D32: =E32+F32 -> -0.35694442 | E32: =-E9*0.05*0.8 -> -0.1920479 | F32: =-F9*0.05*0.8 -> -0.16489652 | G32: =-G9*0.05*0.8 -> -0.34049832 | H32: =-H9*0.05*0.8 -> -0.12748068 | I32: =-I9*0.05*0.8 -> -0.26937055 | J32: =-J9*0.05*0.8 -> 0 | K32: =-K9*0.05*0.8 -> -0.037635547 | L32: =-L9*0.05*0.8 -> 0
A33: 6 | B33: Баланс взаиморасчетов (без учета ГУ) | C33: =SUM(D33,G33:L33) -> -10.674039 | D33: =E33+F33 -> -11.053665 | E33: =SUM(E34:E36) -> -6.7614106 | F33: =SUM(F34:F36) -> -4.2922545 | G33: =SUM(G34:G36) -> 9.6887035 | H33: =SUM(H34:H36) -> -4.7638613 | I33: =SUM(I34:I36) -> -3.23223 | J33: =SUM(J34:J36) -> 2.4999998e-09 | K33: =SUM(K34:K36) -> -1.3964 | L33: =SUM(L34:L36) -> 0.08341449
A34: 6.1. | B34: по БГ | C34: =SUM(D34,G34:L34) -> 13.189969 | D34: =E34+F34 -> -4.2237158 | E34: =E28+E23 -> -3.0644952 | F34: =F28+F23 -> -1.1592207 | G34: =G28+G23 -> 18.944667 | H34: =H28+H23 -> -2.4478943e-09 | I34: =I28+I23 -> -1.5309821 | J34: =J28+J23 -> 0 | K34: =K28+K23 -> 0 | L34: =L28+L23 -> 0
A35: 6.2. | B35: по НЗП | C35: =SUM(D35,G35:L35) -> -17.957782 | D35: =E35+F35 -> -6.7819439 | E35: =E29+E24 -> -3.6489101 | F35: =F29+F24 -> -3.1330338 | G35: =G29+G24 -> -6.469468 | H35: =H29+H24 -> -2.4221329 | I35: =I29+I24 -> -1.652576 | J35: =J29+J24 -> 0 | K35: =K29+K24 -> -0.7150754 | L35: =L29+L24 -> 0.08341449
A36: 6.3. | B36: по ДЗ/КЗ | C36: =SUM(D36,G36:L36) -> -5.9062259 | D36: =E36+F36 -> -0.048005392 | E36: =E25+E26 -> -0.048005392 | F36: =F25+F26 -> 2.220446e-16 | G36: =G25+G26 -> -2.7864955 | H36: =H25+H26 -> -2.3417284 | I36: =I25+I26 -> -0.048671887 | J36: =J25+J26 -> 2.4999998e-09 | K36: =K25+K26 -> -0.68132464 | L36: =L25+L26 -> -1.7347235e-18

Sheet Баланс ФЭК (валюта) без НДС
A1: № п/п | B1: НАИМЕПодрядчик 4НИЕ | C1: ВСЕГО млн USD с НДС | D1: Подрядчик 1 | E1: Подрядчик 1 | F1: Подрядчик 1 | G1: Подрядчик 2 | H1: Подрядчик 2 | I1: Подрядчик 3 | J1: Подрядчик 3 | K1: Подрядчик 3 | L1: Подрядчик 17 | M1: млн в валюте контракта без НДС | N1: дата актуальности НЗП | O1: ='Преза НЗП без НДС'!AO1 -> 46280
B2: договор | E2: Дог.9756 | F2: Дог.10675 | G2: Дог.10221 | H2: Дог.11996 | I2: Дог.10321 | J2: Дог.10321-5 | K2: Дог.11980 | L2: Дог.11820
B3: вид работ/проект | E3: Монолит | F3: ММР ЭМР | G3: монолит ПС и ОЗХ | H3: ММР ПС | I3: ГП мПЭ | J3: Резервуары готовой продукци | K3: Резервуары готовой продукци | L3: Монтаж МК
B4: курс | E4: 89.79 | F4: 80 | G4: 91.5 | H4: 80 | I4: 80 | J4: 80 | K4: 85 | L4: 80
A5: 1 | B5: Стоимость работ по контракту | C5: =SUM(D5,G5:L5) -> 509.67602 | D5: =E5+F5 -> 234.62339 | E5: 64.118612 | F5: 170.50478 | G5: 76.66691 | H5: 104.35444 | I5: 75.531076 | J5: 1.034115 | K5: 16.593551 | L5: 0.87254654
A6: 2 | B6: Выполнение всего, в том числе | C6: =SUM(D6,G6:L6) -> 170.55295 | D6: =E6+F6 -> 67.425432 | E6: =E7+E8 -> 47.880301 | F6: =F7+F8 -> 19.545131 | G6: =G7+G8 -> 55.94228 | H6: =H7+H8 -> 15.81717 | I6: =I7+I8 -> 25.349626 | J6: =J7+J8 -> 0.75476596 | K6: =K7+K8 -> 5.1651585 | L6: =L7+L8 -> 0.0985149
A7: 2.1. | B7: Принято (КС-2) | C7: =SUM(D7,G7:L7) -> 147.35767 | D7: =E7+F7 -> 60.110997 | E7: 43.944893 | F7: 16.166104 | G7: 48.964855 | H7: 13.204861 | I7: 19.829738 | J7: 0.75476596 | K7: 4.3939382 | L7: 0.0985149
A8: 2.2. | B8: НЗП | C8: =SUM(D8,G8:L8) -> 23.195277 | D8: =E8+F8 -> 7.3144348 | E8: ='Баланс ФЭК (валюта) с НДС'!E9/1.22 -> 3.9354077 | F8: ='Баланс ФЭК (валюта) с НДС'!F9/1.22 -> 3.379027 | G8: ='Баланс ФЭК (валюта) с НДС'!G9/1.22 -> 6.9774245 | H8: ='Баланс ФЭК (валюта) с НДС'!H9/1.22 -> 2.612309 | I8: ='Баланс ФЭК (валюта) с НДС'!I9/1.22 -> 5.5198882 | J8: ='Баланс ФЭК (валюта) с НДС'!J9/1.22 -> 0 | K8: ='Баланс ФЭК (валюта) с НДС'!K9/1.22 -> 0.77122023 | L8: ='Баланс ФЭК (валюта) с НДС'!L9/1.22 -> 0
A9: 3 | B9: Профинансировано всего, в т.ч. | C9: =SUM(D9,G9:L9) -> 283.78767 | D9: =E9+F9 -> 158.93244 | E9: =E10+E14 -> 65.542718 | F9: =F10+F14 -> 93.389717 | G9: =G10+G14 -> 60.851833 | H9: =H10+H14 -> 26.431864 | I9: =I10+I14 -> 33.071311 | J9: =J10+J14 -> 0.71894366 | K9: =K10+K14 -> 3.619345 | L9: =L10+L14 -> 0.16193496
A10: 3.1. | B10: Выплачено по КС | C10: =SUM(D10,G10:L10) -> 106.17487 | D10: =E10+F10 -> 44.97155 | E10: =E11+E12+E13 -> 37.260735 | F10: =F11+F12+F13 -> 7.7108149 | G10: =G11+G12+G13 -> 31.183507 | H10: =H11+H12+H13 -> 10.778699 | I10: =I11+I12+I13 -> 14.843351 | J10: =J11+J12+J13 -> 0.71894366 | K10: =K11+K12+K13 -> 3.619345 | L10: =L11+L12+L13 -> 0.05947594
A11: 3.1.1. | B11: Прямая оплата | C11: =SUM(D11,G11:L11) -> 39.33648 | D11: =E11+F11 -> 17.858759 | E11: 14.735651 | F11: 3.1231086 | G11: 14.598508 | H11: 1.2880489 | I11: 5.2339008 | J11: 0 | K11: 0.29778665 | L11: 0.05947594
A12: 3.1.2. | B12: По факторингу | C12: =SUM(D12,G12:L12) -> 60.34538 | D12: =E12+F12 -> 24.549943 | E12: 16.797983 | F12: 7.7519594 | G12: 14.791036 | H12: 8.2987731 | I12: 8.8514532 | J12: 0.61461644 | K12: 3.239558 | L12: 0
A13: 3.1.3. | B13: Взаимозачет | C13: =SUM(D13,G13:L13) -> 6.4930124 | D13: =E13+F13 -> 2.562848 | E13: 5.7271011 | F13: -3.1642531 | G13: 1.7939631 | H13: 1.1918767 | I13: 0.75799706 | J13: 0.10432722 | K13: 0.082000362 | L13: 0
A14: 3.2. | B14: Авансы | C14: =SUM(D14,G14:L14) -> 177.6128 | D14: =E14+F14 -> 113.96089 | E14: =E15+E16 -> 28.281983 | F14: =F15+F16 -> 85.678902 | G14: =G15+G16 -> 29.668326 | H14: =H15+H16 -> 15.653166 | I14: =I15+I16 -> 18.22796 | J14: =J15+J16 -> 0 | K14: =K15+K16 -> 0 | L14: =L15+L16 -> 0.10245902
A15: 3.2.1. | B15: Авансы под БГ | C15: =SUM(D15,G15:L15) -> 158.10587 | D15: =E15+F15 -> 106.96779 | E15: 27.140381 | F15: 79.827411 | G15: 23.084075 | H15: 15.653166 | I15: 12.400841 | J15: 0 | K15: 0 | L15: 0
A16: 3.2.2. | B16: Авансы ОБС / НЗП | C16: =SUM(D16,G16:L16) -> 19.506923 | D16: =E16+F16 -> 6.9930937 | E16: 1.1416027 | F16: 5.851491 | G16: 6.5842511 | H16: 0 | I16: 5.8271189 | J16: 0 | K16: 0 | L16: 0.10245902
A17: 3.3. | B17: Зачет аванса | C17: =SUM(D17,G17:L17) -> 30.37063 | D17: =E17+F17 -> 12.417581 | E17: 4.6348935 | F17: 7.7826876 | G17: 13.884836 | H17: 5.8207661e-17 | I17: 4.0341267 | J17: 0 | K17: 0 | L17: 0.034086484
A18: 3.3.1. | B18: Зачет под БГ | C18: =SUM(D18,G18:L18) -> 13.626019 | D18: =E18+F18 -> 5.4184076 | E18: 3.4943899 | F18: 1.9240177 | G18: 7.1772316 | H18: 0 | I18: 1.0303793 | J18: 0 | K18: 0 | L18: 0
A19: 3.3.2. | B19: Зачет под ОБС / НЗП | C19: =SUM(D19,G19:L19) -> 16.744612 | D19: =E19+F19 -> 6.9991735 | E19: =E17-E18 -> 1.1405036 | F19: =F17-F18 -> 5.8586699 | G19: =G17-G18 -> 6.7076042 | H19: =H17-H18 -> 5.8207661e-17 | I19: =I17-I18 -> 3.0037474 | J19: =J17-J18 -> 0 | K19: =K17-K18 -> 0 | L19: =L17-L18 -> 0.034086484
A20: 4 | B20: Задолженность всего, в т.ч. | C20: =SUM(D20,G20:L20) -> 142.82451 | D20: =E20+F20 -> 101.67693 | E20: =E21+E24+E25 -> 23.724303 | F20: =F21+F24+F25 -> 77.952629 | G20: =G21+G24+G25 -> 13.655485 | H20: =H21+H24+H25 -> 13.743439 | I20: =I21+I24+I25 -> 14.233266 | J20: =J21+J24+J25 -> 0.0019159952 | K20: =K21+K24+K25 -> -0.5548963 | L20: =L21+L24+L25 -> 0.06837253
A21: 4.1. | B21: Остаток незачтенного аванса | C21: =SUM(D21,G21:L21) -> 147.24217 | D21: =E21+F21 -> 101.5433 | E21: =E14-E17 -> 23.64709 | F21: =F14-F17 -> 77.896214 | G21: =G14-G17 -> 15.78349 | H21: =H14-H17 -> 15.653166 | I21: =I14-I17 -> 14.193833 | J21: =J14-J17 -> 0 | K21: =K14-K17 -> 0 | L21: =L14-L17 -> 0.068372536
A22: 4.1.1. | B22: НЗА под БГ | C22: =SUM(D22,G22:L22) -> 144.47985 | D22: =E22+F22 -> 101.54938 | E22: =E15-E18 -> 23.645991 | F22: =F15-F18 -> 77.903393 | G22: =G15-G18 -> 15.906843 | H22: =H15-H18 -> 15.653166 | I22: =I15-I18 -> 11.370462 | J22: =J15-J18 -> 0 | K22: =K15-K18 -> 0 | L22: =L15-L18 -> 0 | M22: =F22+5.9 -> 83.803393
A23: 4.1.2. | B23: НЗА под ОБС / НЗП | C23: =SUM(D23,G23:L23) -> 2.7623112 | D23: =E23+F23 -> -0.0060798049 | E23: =E16-E19 -> 0.0010991269 | F23: =F16-F19 -> -0.0071789319 | G23: =G16-G19 -> -0.12335309 | H23: =H16-H19 -> -5.8207661e-17 | I23: =I16-I19 -> 2.8233716 | J23: =J16-J19 -> 0 | K23: =K16-K19 -> 0 | L23: =L16-L19 -> 0.068372536
A24: 4.2. | B24: Кредиторская задолженность | C24: =SUM(D24,G24:L24) -> -4.4176511 | D24: =E24+F24 -> 0.13362812 | E24: =-(E7-E10-E17+E30) -> 0.077213439 | F24: =-(F7-F10-F17+F30) -> 0.056414679 | G24: =-(G7-G10-G17+G30) -> -2.128005 | H24: =-(H7-H10-H17+H30) -> -1.9097264 | I24: =-(I7-I10-I17+I30) -> 0.039432468 | J24: =-(J7-J10-J17+J30) -> 0.0019159952 | K24: =-(K7-K10-K17+K30) -> -0.5548963 | L24: =-(L7-L10-L17+L30) -> -6.3934426e-09
A25: 4.3. | B25: Неисполненные встречные требования | C25: =SUM(D25,G25:L25) -> 0 | D25: =E25+F25 -> 0 | E25: 0 | F25: 0 | G25: 0 | H25: 0 | I25: 0 | J25: 0 | K25: 0 | L25: 0
A26: 5 | B26: Обеспечение | C26: =SUM(D26,G26:L26) -> -156.59654 | D26: =E26+F26 -> -112.15924 | E26: =SUM(E27:E29) -> -31.046118 | F26: =SUM(F27:F29) -> -81.11312 | G26: =SUM(G27:G29) -> -7.3504464 | H26: =SUM(H27:H29) -> -18.259448 | I26: =SUM(I27:I29) -> -17.948042 | J26: =SUM(J27:J29) -> -0.0377383 | K26: =SUM(K27:K29) -> -0.83667309 | L26: =SUM(L27:L29) -> -0.00495247
A27: 5.1. | B27: Банковская гарантия | C27: =SUM(D27,G27:L27) -> -131.6458 | D27: =E27+F27 -> -103.4522 | E27: -25.771314 | F27: -77.680882 | G27: 0 | H27: -15.653166 | I27: -12.540439 | J27: 0 | K27: 0 | L27: 0
A28: 5.2. | B28: НЗП * 0,8 (коэф.конс) | C28: =SUM(D28,G28:L28) -> -17.62841 | D28: =E28+F28 -> -5.5589704 | E28: =-E8*0.95*0.8 -> -2.9909099 | F28: =-F8*0.95*0.8 -> -2.5680605 | G28: =-G8*0.95*0.8 -> -5.3028427 | H28: =-H8*0.95*0.8 -> -1.9853548 | I28: =-I8*0.95*0.8 -> -4.195115 | J28: =-J8*0.95*0.8 -> 0 | K28: =-K8*0.95*0.8 -> -0.58612738 | L28: =-L8*0.95*0.8 -> 0
A29: 5.3. | B29: ГУ | C29: =SUM(D29,G29:L29) -> -7.322328 | D29: =E29+F29 -> -3.1480718 | E29: =SUM(E30:E31) -> -2.2838944 | F29: =SUM(F30:F31) -> -0.86417739 | G29: =SUM(G30:G31) -> -2.0476038 | H29: =SUM(H30:H31) -> -0.62092775 | I29: =SUM(I30:I31) -> -1.2124882 | J29: =SUM(J30:J31) -> -0.0377383 | K29: =SUM(K30:K31) -> -0.25054571 | L29: =SUM(L30:L31) -> -0.00495247
A30: 5.3.1. | B30: ГУ с принятых работ | C30: =SUM(D30,G30:L30) -> -6.3945169 | D30: =E30+F30 -> -2.8554944 | E30: -2.1264781 | F30: -0.72901631 | G30: -1.7685068 | H30: -0.51643539 | I30: -0.9916927 | J30: -0.0377383 | K30: -0.2196969 | L30: -0.00495247
A31: 5.3.2. | B31: ГУ с НЗП | C31: =SUM(D31,G31:L31) -> -0.92781107 | D31: =E31+F31 -> -0.29257739 | E31: =-E8*0.05*0.8 -> -0.15741631 | F31: =-F8*0.05*0.8 -> -0.13516108 | G31: =-G8*0.05*0.8 -> -0.27909698 | H31: =-H8*0.05*0.8 -> -0.10449236 | I31: =-I8*0.05*0.8 -> -0.22079553 | J31: =-J8*0.05*0.8 -> 0 | K31: =-K8*0.05*0.8 -> -0.030848809 | L31: =-L8*0.05*0.8 -> 0
A32: 6 | B32: Баланс взаиморасчетов (без учета ГУ) | C32: =SUM(D32,G32:L32) -> -6.4496964 | D32: =E32+F32 -> -7.3342341 | E32: =SUM(E33:E35) -> -5.0379205 | F32: =SUM(F33:F35) -> -2.2963136 | G32: =SUM(G33:G35) -> 8.3526423 | H32: =SUM(H33:H35) -> -3.8950812 | I32: =SUM(I33:I35) -> -2.5022883 | J32: =SUM(J33:J35) -> 0.0019159952 | K32: =SUM(K33:K35) -> -1.1410237 | L32: =SUM(L33:L35) -> 0.06837253
A33: 6.1. | B33: по БГ | C33: =SUM(D33,G33:L33) -> 12.834054 | D33: =E33+F33 -> -1.902812 | E33: =E27+E22 -> -2.1253232 | F33: =F27+F22 -> 0.22251121 | G33: =G27+G22 -> 15.906843 | H33: =H27+H22 -> -4.9572915e-09 | I33: =I27+I22 -> -1.1699772 | J33: =J27+J22 -> 0 | K33: =K27+K22 -> 0 | L33: =L27+L22 -> 0
A34: 6.2. | B34: по НЗП | C34: =SUM(D34,G34:L34) -> -14.866099 | D34: =E34+F34 -> -5.5650502 | E34: =E28+E23 -> -2.9898108 | F34: =F28+F23 -> -2.5752395 | G34: =G28+G23 -> -5.4261957 | H34: =H28+H23 -> -1.9853548 | I34: =I28+I23 -> -1.3717435 | J34: =J28+J23 -> 0 | K34: =K28+K23 -> -0.58612738 | L34: =L28+L23 -> 0.068372536
A35: 6.3. | B35: по ДЗ/КЗ | C35: =SUM(D35,G35:L35) -> -4.4176511 | D35: =E35+F35 -> 0.13362812 | E35: =E24+E25 -> 0.077213439 | F35: =F24+F25 -> 0.056414679 | G35: =G24+G25 -> -2.128005 | H35: =H24+H25 -> -1.9097264 | I35: =I24+I25 -> 0.039432468 | J35: =J24+J25 -> 0.0019159952 | K35: =K24+K25 -> -0.5548963 | L35: =L24+L25 -> -6.3934426e-09

Sheet Преза НЗП без НДС
A1: № п/п | B1: НАИМЕПодрядчик 4НИЕ | C1: ВСЕГО руб. | D1: Подрядчик 1 | E1: Подрядчик 1 | F1: Подрядчик 1 | G1: Подрядчик 2 | H1: Подрядчик 2 | I1: Подрядчик 3 | J1: Подрядчик 3 | K1: Подрядчик 3 | L1: Подрядчик 4 | M1: Подрядчик 5 | N1: Подрядчик 8 | O1: Подрядчик 9 | P1: Подрядчик 6 | Q1: Подрядчик 10 | R1: Подрядчик 10 | S1: Подрядчик 10 | T1: Подрядчик 11 | U1: Подрядчик 12 | V1: Подрядчик 13 | W1: Подрядчик 11 | X1: Подрядчик 14 | Y1: Подрядчик 15 | Z1: Подрядчик 15 | AA1: Подрядчик 15 | AB1: Подрядчик 16 | AC1: Подрядчик 18 | AD1: Подрядчик 18 | AE1: Подрядчик 19 | AF1: Подрядчик 25 | AG1: Подрядчик 25 | AH1: Подрядчик 25 | AI1: Подрядчик 23 | AJ1: Подрядчик 21 | AK1: Подрядчик 7 | AL1: Подрядчик 22 | AM1: млн руб. без НДС | AN1: дата актуальности НЗП | AO1: 46280
E2: Дог.9756 | F2: Дог.10675 | G2: Дог.10221 | H2: Дог.11996 | I2: Дог.10321 | J2: Дог.10321-5 | K2: Дог.11980 | L2: Дог.10539 | M2: Дог.10988 | N2: Дог.7038 | O2: Дог.7043 | P2: Дог.11458 | R2: Дог.8833 | S2: Дог.9211 | U2: Дог.8713 | V2: НГ.12 | W2: Дог.8714 | X2: Дог.6016 | Z2: Дог.7766 | AA2: Дог.7766-2 | AB2: Дог.10434 | AC2: Дог.10144 | AD2: Дог.10148 | AE2: Дог.9305-1 | AF2: Дог.5348-8 | AG2: Дог.5348-9 | AH2: Дог.10965 | AI2: Дог.8172 | AJ2: Дог.10619 | AK2: Дог.12009 | AL2: Дог.10937
B3: вид работ/проект | E3: Монолит | F3: ММР ЭМР | G3: монолит ПС и ОЗХ | H3: ММР ПС | I3: ГП мПЭ | J3: сц МОНОЛИТ ИЗЪЯТИЕ | K3: Резервуары готовой продукци | L3: Эстакады ОЗХ | N3: СЦ | O3: СЦ | P3: Водооборотный цикл | R3: СЦ | S3: ПЭ | U3: ЭБСМ | V3: ПС и ОЗХ | W3: ПЭ | Z3: СЦ | AA3: ПЭ | AI3: Объемы Ямата по ОЗХ | AK3: Подстанции и сети
B4: курс | E4: 89.79 | F4: 80 | G4: 91.5 | H4: 80 | I4: 80 | J4: 80 | K4: 85 | L4: 1 | M4: 1 | N4: 1 | O4: 1 | P4: 1 | R4: 1 | S4: 1 | U4: 1 | V4: 1 | W4: 1 | X4: 1 | Z4: 1 | AA4: 1 | AB4: 1 | AC4: 1 | AD4: 1 | AE4: 1 | AF4: 1 | AG4: 1 | AH4: 1 | AI4: 1 | AJ4: 1 | AK4: 1 | AL4: 1
A5: 1 | B5: Стоимость работ по контракту | C5: =SUM(N5:Q5,T5,X5:Y5,G5,D5,L5:AI5) -> 56216.298 | D5: =E5+F5 -> 17181.071 | E5: 6206.1602 | F5: 10974.911 | G5: 7015.0223 | H5: 8387.0997 | I5: 6198.0332 | J5: 100.92962 | K5: 1898.418 | L5: 9110.9145 | M5: 4546.6239 | N5: 1137.902 | O5: 419.8227 | P5: 3013.3477 | Q5: 1605.12 | R5: 497.44458 | S5: 497.44458 | T5: =SUM(U5:W5) -> 225.60021 | U5: 58.717439 | V5: 95.194727 | W5: 71.688045 | X5: 685.88079 | Y5: =Z5+AA5 -> 629.69975 | Z5: 597.01903 | AA5: 32.680717 | AB5: 316.66288 | AC5: 144.15474 | AD5: 34.119971 | AE5: 40.625317 | AF5: 29.623627 | AG5: 18.829093 | AH5: 130.12092 | AI5: 363.5939 | AJ5: 29.785632 | AK5: 2921.6901 | AL5: 230.12225
A6: 2 | B6: Выполнение всего, в том числе | C6: =SUM(N6:Q6,T6,X6:Y6,G6,D6,L6:AI6) -> 25612.194 | D6: =E6+F6 -> 5861.9409 | E6: 4286.0272 | F6: 1575.9138 | G6: 5103.445 | H6: 1276.2776 | I6: 2028.7256 | J6: =J7+J8 -> 58.62626 | K6: 435.28087 | L6: 2268.0884 | M6: 1215.1726 | N6: 770 | O6: 336.06928 | P6: 572.48465 | Q6: 1242.354 | R6: 367.00116 | S6: 361.77218 | T6: =SUM(U6:W6) -> 214.98886 | U6: 55.071739 | V6: 88.374455 | W6: 71.542663 | X6: 681 | Y6: =Z6+AA6 -> 595.997 | Z6: 560 | AA6: =AA7+AA8 -> 35.996999 | AB6: 315 | AC6: 103 | AD6: 46 | AE6: 51 | AF6: 8 | AG6: 83 | AH6: 66 | AI6: 126 | AJ6: 17 | AK6: 82.434184 | AL6: =AL7+AL8 -> 9.9533775
A7: 2.1. | B7: Принято (КС-2) | C7: =SUM(N7:Q7,T7,X7:Y7,G7,D7,L7:AI7) -> 24029.684 | D7: =E7+F7 -> 5241.5778 | E7: 3945.812 | F7: 1295.7658 | G7: 4480.2842 | H7: 1067.2929 | I7: 1556.6765 | J7: 58.62626 | K7: 345.52627 | L7: 1737.9923 | M7: 1070.5368 | N7: 660.26948 | O7: 335.76928 | P7: 432.19952 | Q7: =R7+S7 -> 1322.4965 | R7: 956.74052 | S7: 365.75594 | T7: =SUM(U7:W7) -> 214.40195 | U7: 55.071857 | V7: 87.787424 | W7: 71.542667 | X7: 681.4771 | Y7: =Z7+AA7 -> 607.3571 | Z7: 571.3601 | AA7: 35.996999 | AB7: 314.7882 | AC7: 102.75185 | AD7: 46.05876 | AE7: 50.827605 | AF7: 8.2055968 | AG7: 82.964134 | AH7: 86.410763 | AI7: 155.08908 | AJ7: 18.095674 | AK7: 19.695793 | AL7: 9.9533775
A8: 2.2. | B8: НЗП | C8: =SUM(N8:Q8,T8,X8:Y8,G8,D8,L8:AI8) -> 132 | D8: =E8+F8 -> 0 | E8: =E30 -> 0 | F8: =F30 -> 0 | G8: =G30 -> 0 | H8: =H30 -> 0 | I8: =I30 -> 0 | J8: =J30 -> 0 | K8: =K30 -> 0 | L8: =L30 -> 0 | ... P8: =P30 -> 0 | Q8: =R8+S8 -> 0 | R8: =R30 -> 0 | S8: =S30 -> 0 | T8: =SUM(U8:W8) -> 0 | U8: =U30 -> 0 | V8: =V30 -> 0 | W8: =W30 -> 0 | X8: =X30 -> 0 | Y8: =Z8+AA8 -> 44 | Z8: 44 | AA8: =AA30 -> 0 | AB8: =AB30 -> 0 | AC8: =AC30 -> 0 | AD8: =AD30 -> 0 | AE8: =AE30 -> 0 | AF8: =AF30 -> 0 | AG8: =AG30 -> 0 | AH8: =AH30 -> 0 | ... AL8: =AL30 -> 0
A9: 2.3. | B9: Доля НЗП от выполненных работ | C9: =IFERROR(C8/C6,) -> 0.0051537952 | D9: =IFERROR(D8/D6,) -> 0 | E9: =IFERROR(E8/E6,) -> 0 | F9: =IFERROR(F8/F6,) -> 0 | G9: =IFERROR(G8/G6,) -> 0 | H9: =IFERROR(H8/H6,) -> 0 | I9: =IFERROR(I8/I6,) -> 0 | J9: =IFERROR(J8/J6,) -> 0 | ... AL9: =IFERROR(AL8/AL6,) -> 0
A10: 3 | B10: Неисполненные встречные требования заказчика | C10: =SUM(N10:Q10,T10,X10:Y10,G10,D10,L10:AI10) -> 0 | D10: =E10+F10 -> 0 | E10: 0 | F10: 0 | G10: 0 | H10: 0 | I10: 0 | J10: 0 | K10: 0 | L10: 0 | M10: 0 | N10: 0 | O10: 0 | P10: 0 | Q10: =R10+S10 -> 0 | R10: 0 | S10: 0 | T10: =SUM(U10:W10) -> 0 | U10: 0 | V10: 0 | W10: 0 | X10: 0 | Y10: =Z10+AA10 -> 0 | Z10: 0 | AA10: 0 | AB10: 0 | AC10: 0 | AD10: 0 | AE10: 0 | AF10: 0 | AG10: 0 | AH10: 0 | AI10: 0 | AJ10: 0 | AK10: 0 | AL10: 0
A11: 4 | B11: Профинансировано всего | C11: =SUM(N11:Q11,T11,X11:Y11,G11,D11,L11:AI11) -> 35303.426 | D11: =E11+F11 -> 13405.817 | E11: =SUM(E12:E14,E16) -> 5883.3652 | F11: =SUM(F12:F14,F16) -> 7522.4515 | G11: =SUM(G12:G14,G16) -> 5571.4573 | H11: =SUM(H12:H14,H16) -> 1977.257 | I11: =SUM(I12:I14,I16) -> 2663.0893 | J11: =SUM(J12:J14,J16) -> 58.023472 | K11: =SUM(K12:K14,K16) -> 308.11947 | L11: =SUM(L12:L14,L16) -> 3807.0302 | ... P11: =SUM(P12:P14,P16) -> 411.03424 | Q11: =R11+S11 -> 1362.5561 | R11: =SUM(R12:R14,R16) -> 1077.1006 | S11: =SUM(S12:S14,S16) -> 285.45549 | T11: =SUM(U11:W11) -> 203.01673 | U11: =SUM(U12:U14,U16) -> 52.399822 | V11: =SUM(V12:V14,V16) -> 79.074245 | W11: =SUM(W12:W14,W16) -> 71.542667 | X11: =SUM(X12:X14,X16) -> 694.70803 | Y11: =Z11+AA11 -> 490.11835 | Z11: =SUM(Z12:Z14,Z16) -> 460.70571 | AA11: =SUM(AA12:AA14,AA16) -> 29.412646 | AB11: =SUM(AB12:AB14,AB16) -> 300.17192 | AC11: =SUM(AC12:AC14,AC16) -> 85.615963 | AD11: =SUM(AD12:AD14,AD16) -> 39.163117 | AE11: =SUM(AE12:AE14,AE16) -> 45.794844 | AF11: =SUM(AF12:AF14,AF16) -> 7.7976955 | AG11: =SUM(AG12:AG14,AG16) -> 79.159626 | ... AL11: =SUM(AL12:AL14,AL16) -> 8.9580398
A12: 4.1.1. | B12: Выплачено по КС | C12: =SUM(N12:Q12,T12,X12:Y12,G12,D12,L12:AI12) -> 9692.3853 | D12: =E12+F12 -> 1785.4397 | E12: 1835.635 | F12: -50.195312 | G12: 1499.9111 | H12: 187.4587 | I12: 485.82212 | J12: 8.3461772 | K12: 32.338655 | L12: 61.301987 | M12: 63.845408 | N12: 593.06931 | O12: 302.10801 | P12: 77.717166 | Q12: =R12+S12 -> 545.03597 | R12: 465.49329 | S12: 79.54268 | T12: =SUM(U12:W12) -> 171.42069 | U12: 52.399822 | V12: 66.749457 | W12: 52.271408 | X12: 251.36558 | Y12: =Z12+AA12 -> 330.11835 | Z12: 300.70571 | AA12: 29.412646 | AB12: 265.94192 | AC12: 85.615963 | AD12: 39.163117 | AE12: 37.461511 | AF12: 7.7976955 | AG12: 79.159626 | AH12: 65.513024 | AI12: 112.9891 | AJ12: 16.419933 | AK12: 1.2229 | AL12: 8.9580398
A13: 4.1.2. | B13: Выплачено по КС (ком. кредит) | D13: =E13+F13 -> 2129.5133 | E13: 1508.2909 | F13: 621.22235 | G13: 1353.3798 | H13: 672.60839 | I13: 713.02857 | J13: 49.677295 | K13: 275.78082 | L13: 1087.0391 | M13: 798.63734 | N13: 0 | O13: 0 | P13: 286.59576 | R13: 171.28284 | S13: 28.597964 | U13: 0 | V13: 0 | W13: 0 | X13: 0 | Y13: =Z13+AA13 -> 0 | Z13: 0 | AA13: 0 | AB13: 0 | AC13: 0 | AD13: 0 | AE13: 0 | AF13: 0 | AG13: 0 | AH13: 0 | AI13: 0 | AJ13: 0 | AK13: 0 | AL13: 0
A14: 4.2. | B14: Авансы под БГ | C14: =SUM(N14:Q14,T14,X14:Y14,G14,D14,L14:AI14) -> 15552.365 | D14: =E14+F14 -> 8866.9885 | E14: 2436.9348 | F14: 6430.0537 | G14: 2115.7074 | H14: 1117.1899 | I14: 995.76047 | J14: 0 | K14: 0 | L14: 2658.6891 | M14: 739.0212 | N14: 0 | O14: 0 | P14: 0 | Q14: =R14+S14 -> 0 | R14: 0 | S14: 0 | T14: =SUM(U14:W14) -> 0 | U14: 0 | V14: 0 | W14: 0 | X14: 318.4475 | Y14: =Z14+AA14 -> 160 | Z14: 160 | AA14: 0 | AB14: 34.23 | AC14: 0 | AD14: 0 | AE14: 8.3333333 | AF14: 0 | AG14: 0 | AH14: 0 | AI14: 12.5 | AJ14: 0 | AK14: 876.50703 | AL14: 0
A15: 4.3. | B15: Зачет аванса | C15: =SUM(N15:Q15,T15,X15:Y15,G15,D15,L15:AI15) -> -5971.4071 | D15: =E15+F15 -> -1093.0078 | E15: -416.16709 | F15: -676.84074 | G15: -1270.4625 | H15: -3.7252903e-15 | I15: -320.01176 | J15: 0 | K15: 0 | L15: -511.62423 | M15: -155.29963 | N15: 0 | O15: 0 | P15: -46.721311 | Q15: =R15+S15 -> -452.30789 | R15: -274.99305 | S15: -177.31485 | T15: =SUM(U15:W15) -> -22.966148 | U15: 0 | V15: -12.324788 | W15: -10.64136 | X15: -443.34245 | Y15: =Z15+AA15 -> -160 | Z15: -160 | AA15: 0 | AB15: -34.23 | AC15: 0 | AD15: 0 | AE15: -8.3333333 | AF15: 0 | AG15: 0 | AH15: 0 | AI15: -12.5 | AJ15: 0 | AK15: -5.9087379 | AL15: 0
A16: 4.4. | B16: Авансы на ОБС | C16: =SUM(N16:Q16,T16,X16:Y16,G16,D16,L16:AI16) -> 3517.2729 | D16: =E16+F16 -> 623.87528 | E16: 102.50451 | F16: 521.37078 | G16: 602.45898 | H16: 0 | I16: 468.47809 | J16: 0 | K16: 0 | L16: 0 | M16: 0 | N16: 0 | O16: 0 | P16: 46.721311 | Q16: =R16+S16 -> 617.63934 | R16: 440.32449 | S16: 177.31485 | T16: =SUM(U16:W16) -> 31.596047 | U16: 0 | V16: 12.324788 | W16: 19.271258 | X16: 124.89495 | Y16: =Z16+AA16 -> 0 | Z16: 0 | AA16: 0 | AB16: 0 | AC16: 0 | AD16: 0 | AE16: 0 | AF16: 0 | AG16: 0 | AH16: 0 | AI16: 0 | AJ16: 0 | AK16: 0 | AL16: 0
A17: 5 | B17: Задолженность всего | C17: =SUM(N17:Q17,T17,X17:Y17,G17,D17,L17:AI17) -> 6729.8517 | D17: =E17+F17 -> 8164.239 | E17: =SUM(E18:E22) -> 1937.5533 | F17: =SUM(F18:F22) -> 6226.6858 | G17: =SUM(G18:G22) -> -262.20674 | H17: =SUM(H18:H22) -> 237.35575 | I17: =SUM(I18:I22) -> 393.38419 | J17: =SUM(J18:J22) -> -50.280083 | K17: =SUM(K18:K22) -> -313.18761 | L17: =SUM(L18:L22) -> 981.99876 | ... P17: =SUM(P18:P22) -> -307.76104 | Q17: =R17+S17 -> -159.82116 | R17: =SUM(R18:R22) -> -50.922746 | S17: =SUM(S18:S22) -> -108.89842 | T17: =SUM(U17:W17) -> -11.385214 | U17: =SUM(U18:U22) -> -2.6720354 | V17: =SUM(V18:V22) -> -8.7131786 | W17: =SUM(W18:W22) -> -8.8817842e-16 | X17: =SUM(X18:X22) -> 13.230937 | Y17: =Z17+AA17 -> -161.23875 | Z17: =SUM(Z18:Z22) -> -154.65439 | AA17: =SUM(AA18:AA22) -> -6.584353 | AB17: =SUM(AB18:AB22) -> -14.616286 | AC17: =SUM(AC18:AC22) -> -17.135889 | AD17: =SUM(AD18:AD22) -> -6.8956432 | AE17: =SUM(AE18:AE22) -> -5.0327605 | AF17: =SUM(AF18:AF22) -> -0.4079013 | AG17: =SUM(AG18:AG22) -> -3.8045083 | ... AL17: =SUM(AL18:AL22) -> -0.99533775
A18: 5.1. | B18: По авансам | C18: =SUM(N18:Q18,T18,X18:Y18,G18,D18,L18:AI18) -> 13098.23 | D18: =E18+F18 -> 8397.856 | E18: =E14+E16+E15 -> 2123.2722 | F18: =F14+F16+F15 -> 6274.5838 | G18: =G14+G16+G15 -> 1447.7039 | H18: =H14+H16+H15 -> 1117.1899 | I18: =I14+I16+I15 -> 1144.2268 | J18: =J14+J16+J15 -> 0 | K18: =K14+K16+K15 -> 0 | L18: =L14+L16+L15 -> 2147.0649 | ... P18: =P14+P16+P15 -> -5.4098379e-09 | Q18: =R18+S18 -> 165.33145 | R18: =R14+R16+R15 -> 165.33145 | S18: =S14+S16+S15 -> -2.1666693e-08 | T18: =SUM(U18:W18) -> 8.6298987 | U18: =U14+U16+U15 -> 0 | V18: =V14+V16+V15 -> -3.3333336e-09 | W18: =W14+W16+W15 -> 8.6298987 | X18: =X14+X16+X15 -> -3.3332412e-09 | Y18: =Z18+AA18 -> 0 | Z18: =Z14+Z16+Z15 -> 0 | AA18: =AA14+AA16+AA15 -> 0 | AB18: =AB14+AB16+AB15 -> -4.4247628e-10 | AC18: =AC14+AC16+AC15 -> 0 | AD18: =AD14+AD16+AD15 -> 0 | AE18: =AE14+AE16+AE15 -> -1.6666668e-09 | AF18: =AF14+AF16+AF15 -> 0 | AG18: =AG14+AG16+AG15 -> 0 | ... AL18: =AL14+AL16+AL15 -> 0
A19: 5.2. | B19: По выполненным работам «-» * | C19: =SUM(N19:Q19,T19,X19:Y19,G19,D19,L19:AI19) -> -4971.8223 | D19: =E19+F19 -> 15.918289 | E19: =-(E7-E13-E12+E15+E20) -> 5.2175538 | F19: =-(F7-F13-F12+F15+F20) -> 10.700736 | G19: =-(G7-G12+G15+G20) -> -1548.0923 | H19: =-(H7-H12+H15+H20) -> -838.62541 | I19: =-(I7-I12+I15+I20) -> -671.09564 | J19: =-(J7-J12+J15+J20) -> -47.234283 | K19: =-(K7-K12+K15+K20) -> -294.51213 | L19: =-(L7-L12+L15+L20) -> -1078.3626 | M19: =-(M7-M12+M15+M20) -> -797.86494 | N19: =-(N7-N12+N15+N20) -> 1.0493235 | ... P19: =-(P7-P12+P15+P20) -> -286.38839 | Q19: =R19+S19 -> -259.02779 | R19: =-(R7-R12+R15+R20) -> -168.41716 | S19: =-(S7-S12+S15+S20) -> -90.610621 | T19: =SUM(U19:W19) -> -8.4643569 | U19: =-(U7-U12+U15+U20) -> 0.097101597 | V19: =-(V7-V12+V15+V20) -> 0.068440171 | W19: =-(W7-W12+W15+W20) -> -8.6298987 | X19: =-(X7-X12+X15+X20) -> 13.230937 | Y19: =Z19+AA19 -> -56.503036 | Z19: =-(Z7-Z12+Z15+Z20) -> -53.518383 | AA19: =-(AA7-AA12+AA15+AA20) -> -2.9846532 | AB19: =-(AB7-AB12+AB15+AB20) -> 1.0951881 | AC19: =-(AC7-AC12+AC15+AC20) -> -9.6012141 | AD19: =-(AD7-AD12+AD15+AD20) -> -4.1034272 | AE19: =-(AE7-AE12+AE15+AE20) -> 0.050000002 | AF19: =-(AF7-AF12+AF15+AF20) -> 1.6653345e-16 | AG19: =-(AG7-AG12+AG15+AG20) -> 0.19836066 | ... AL19: =-(AL7-AL12+AL15+AL20) -> -8.8817842e-16
A20: 5.3. | B20: Гарантийным удержаниям «-» | C20: =SUM(N20:Q20,T20,X20:Y20,G20,D20,L20:AI20) -> -1264.5563 | D20: =E20+F20 -> -249.53523 | E20: -190.93647 | F20: -58.59876 | G20: -161.81837 | H20: -41.208749 | I20: -79.74698 | J20: -3.0457998 | K20: -18.675477 | L20: -86.703552 | M20: -53.526841 | N20: -68.249489 | O20: -33.719601 | P20: -21.372653 | Q20: =R20+S20 -> -66.124823 | R20: -47.837026 | S20: -18.287797 | T20: =SUM(U20:W20) -> -11.550756 | U20: -2.769137 | V20: -8.7816187 | W20: -1.9999999e-08 | X20: 0 | Y20: =Z20+AA20 -> -60.73571 | Z20: -57.13601 | AA20: -3.5996999 | AB20: -15.711475 | AC20: -7.5346751 | AD20: -2.792216 | AE20: -5.0827605 | AF20: -0.4079013 | AG20: -4.002869 | AH20: 0 | AI20: -15.523067 | AJ20: -0.90478367 | AK20: -1.9695793 | AL20: -0.99533775
A21: 5.4. | B21: Задолженность по НЗП (со знаком "-") | C21: =SUM(N21:Q21,T21,X21:Y21,G21,D21,L21:AI21) -> -132 | D21: =E21+F21 -> 0 | E21: =-E8 -> 0 | F21: =-F8 -> 0 | G21: =-G8 -> 0 | H21: =-H8 -> 0 | I21: =-I8 -> 0 | J21: =-J8 -> 0 | K21: =-K8 -> 0 | L21: =-L8 -> 0 | ... P21: =-P8 -> 0 | Q21: =R21+S21 -> 0 | R21: =-R8 -> 0 | S21: =-S8 -> 0 | T21: =SUM(U21:W21) -> 0 | U21: =-U8 -> 0 | V21: =-V8 -> 0 | W21: =-W8 -> 0 | X21: =-X8 -> 0 | Y21: =Z21+AA21 -> -44 | Z21: =-Z8 -> -44 | AA21: =-AA8 -> 0 | AB21: =-AB8 -> 0 | AC21: =-AC8 -> 0 | AD21: =-AD8 -> 0 | AE21: =-AE8 -> 0 | AF21: =-AF8 -> 0 | AG21: =-AG8 -> 0 | ... AL21: =-AL8 -> 0
A22: 5.5. | B22: Прочие удержания (штрафы, неустойки, проч.) «-» | C22: =SUM(N22:Q22,T22,X22:Y22,G22,D22,L22:AI22) -> 0 | D22: =E22+F22 -> 0 | Q22: =R22+S22 -> 0 | T22: =SUM(U22:W22) -> 0 | Y22: =Z22+AA22 -> 0
A23: 6 | B23: Обеспечение (БГ) | C23: =SUM(N23:Q23,T23,X23:Y23,G23,D23,L23:AI23) -> 11757.246 | D23: =E23+F23 -> 8670.6181 | E23: =SUM(E24:E26) -> 2352.5731 | F23: =SUM(F24:F26) -> 6318.0451 | G23: =SUM(G24:G26) -> 0 | H23: =SUM(H24:H26) -> 1135.8097 | I23: =SUM(I24:I26) -> 1003.3554 | J23: =SUM(J24:J26) -> 0 | K23: =SUM(K24:K26) -> 0 | L23: =SUM(L24:L26) -> 2331.6452 | ... P23: =SUM(P24:P26) -> 0 | Q23: =R23+S23 -> 0 | R23: =SUM(R24:R26) -> 0 | S23: =SUM(S24:S26) -> 0 | T23: =SUM(U23:W23) -> 0 | U23: =SUM(U24:U26) -> 0 | V23: =SUM(V24:V26) -> 0 | W23: =SUM(W24:W26) -> 0 | X23: =SUM(X24:X26) -> 0 | Y23: =Z23+AA23 -> 0 | Z23: =SUM(Z24:Z26) -> 0 | AA23: =SUM(AA24:AA26) -> 0 | AB23: =SUM(AB24:AB26) -> 15.96148 | AC23: =SUM(AC24:AC26) -> 0 | AD23: =SUM(AD24:AD26) -> 0 | AE23: =SUM(AE24:AE26) -> 0 | AF23: =SUM(AF24:AF26) -> 0 | AG23: =SUM(AG24:AG26) -> 0 | ... AL23: =SUM(AL24:AL26) -> 0
A24: 6.1. | B24: Банковская гарантия | C24: =SUM(N24:Q24,T24,X24:Y24,G24,D24,L24:AI24) -> 11757.246 | D24: =E24+F24 -> 8670.6181 | E24: 2352.5731 | F24: 6318.0451 | G24: 0 | H24: 1135.8097 | I24: 1003.3554 | J24: 0 | K24: 0 | L24: 2331.6452 | M24: 739.0212 | N24: 0 | O24: 0 | P24: 0 | Q24: =R24+S24 -> 0 | R24: 0 | S24: 0 | T24: =SUM(U24:W24) -> 0 | U24: 0 | V24: 0 | W24: 0 | X24: 0 | Y24: =Z24+AA24 -> 0 | Z24: 0 | AA24: 0 | AB24: 15.96148 | AC24: 0 | AD24: 0 | AE24: 0 | AF24: 0 | AG24: 0 | AH24: 0 | AI24: 0 | AJ24: 0 | AK24: 876.50703 | AL24: 0
A25: 6.2. | B25: Материалы поставленные на стройплощадку | C25: =SUM(N25:Q25,T25,X25:Y25,G25,D25,L25:AI25) -> 0 | D25: =E25+F25 -> 0 | E25: 0 | F25: 0 | G25: 0 | H25: 0 | I25: 0 | J25: 0 | K25: 0 | L25: 0 | M25: 0 | N25: 0 | O25: 0 | P25: 0 | Q25: =R25+S25 -> 0 | R25: 0 | S25: 0 | T25: =SUM(U25:W25) -> 0 | U25: 0 | V25: 0 | W25: 0 | X25: 0 | Y25: =Z25+AA25 -> 0 | AB25: 0 | AC25: 0 | AD25: 0 | AE25: 0 | AF25: 0 | AG25: 0 | AH25: 0 | AI25: 0 | AJ25: 0 | AK25: 0 | AL25: 0
A26: 6.3. | B26: Иное обеспечение | C26: =SUM(N26:Q26,T26,X26:Y26,G26,D26,L26:AI26) -> 0 | D26: =E26+F26 -> 0 | E26: 0 | F26: 0 | G26: 0 | H26: 0 | I26: 0 | J26: 0 | K26: 0 | L26: 0 | N26: 0 | O26: 0 | P26: 0 | Q26: =R26+S26 -> 0 | T26: =SUM(U26:W26) -> 0 | Y26: =Z26+AA26 -> 0 | AI26: 0 | AK26: 0
A27: 7 | B27: Кредитный риск (с НЗП) | C27: =IF((C11+C10-C6-C23)<=0,"отсутствует",(C11+C10-C6-C23)) -> отсутствует | D27: =IF((D11+D10-D6-D23)<=0,"отсутствует",(D11+D10-D6-D23)) -> отсутствует | E27: =IF((E11+E10-E6-E23)<=0,"отсутствует",(E11+E10-E6-E23)) -> отсутствует | F27: =IF((F11+F10-F6-F23)<=0,"отсутствует",(F11+F10-F6-F23)) -> отсутствует | G27: =IF((G11+G10-G6-G23)<=0,"отсутствует",(G11+G10-G6-G23)) -> 468.01231 | H27: =IF((H11+H10-H6-H23)<=0,"отсутствует",(H11+H10-H6-H23)) -> отсутствует | I27: =IF((I11+I10-I6-I23)<=0,"отсутствует",(I11+I10-I6-I23)) -> отсутствует | J27: =IF((J11+J10-J6-J23)<=0,"отсутствует",(J11+J10-J6-J23)) -> отсутствует | ... AL27: =IF((AL11+AL10-AL6-AL23)<=0,"отсутствует",(AL11+AL10-AL6-AL23)) -> отсутствует
B29: Фактор возникновения НЗП | C29: =SUM(N29:AI29) -> 216.99925 | D29: =SUM(D30:D34) -> 0 | E29: =SUM(E30:E34) -> 182.38241 | F29: =SUM(F30:F34) -> 4.0681463 | G29: =SUM(G30:G34) -> 156.72369 | H29: =SUM(H30:H34) -> 156.72369 | I29: =SUM(I30:I34) -> 69.764678 | J29: =SUM(J30:J34) -> 69.764678 | K29: =SUM(K30:K34) -> 69.764678 | ... X29: =SUM(X30:X34) -> 13.897904 | AA29: =SUM(AA30:AA34) -> 0 | AB29: =SUM(AB30:AB34) -> 0 | AC29: =SUM(AC30:AC34) -> 0 | AD29: =SUM(AD30:AD34) -> 0 | AE29: =SUM(AE30:AE34) -> 0 | AF29: =SUM(AF30:AF34) -> 0 | AG29: =SUM(AG30:AG34) -> 0 | AH29: =SUM(AH30:AH34) -> 0 | ... AL29: =SUM(AL30:AL34) -> 0
A30: 1 | B30: Прогноз КС-2
A31: 2 | B31: Не сданы RFI | C31: =SUM(N31:AI31) -> 106.91603 | E31: 24.766764 | G31: 80.673513 | H31: 80.673513 | I31: 47.449769 | J31: 47.449769 | K31: 47.449769 | L31: 10.898545 | M31: 0 | N31: 35.613356 | O31: -0.00046507774 | P31: 10.898545 | R31: 15.78 | S31: 41.929528 | U31: 0.17264447 | V31: 2.52242 | W31: 0 | X31: 0 | Y31: =Z31+AA31 -> 0
A32: 3 | B32: Неполный комплект ИД | C32: =SUM(N32:AI32) -> 100.86388 | E32: 155.01962 | F32: 4.0681463 | G32: 61.628691 | H32: 61.628691 | I32: 22.31491 | J32: 22.31491 | K32: 22.31491 | L32: 8.3141222 | M32: 1.7483353 | N32: 28.573296 | O32: 5.5226373 | P32: 8.3141222 | R32: 22.435 | S32: 21.967509 | U32: 0.047812637 | V32: 0.10560141 | W32: 0 | X32: 13.897904 | Y32: =Z32+AA32 -> 0
A33: 4 | B33: Прочее | C33: =SUM(N33:AI33) -> 9.2193353 | N33: 6.4065735 | O33: 2.8127617 | V33: 0 | X33: 0 | Y33: =Z33+AA33 -> 0 | Z33: 0
A34: 5 | B34: Нет ЕР | C34: =SUM(N34:AI34) -> 0 | E34: 2.5960217 | G34: 14.421482 | H34: 14.421482 | M34: 6.6309793 | N34: 0 | Y34: =Z34+AA34 -> 0
O54: 243257433
O55: 80
N57: =F1 -> Подрядчик 1 | O57: Ямата ММР | Q57: =I1 -> Подрядчик 3 | T57: =AB1 -> Подрядчик 16 | U57: Подрядчик 2
C58: вид работ | N58: монолит | O58: ММР ЭМР | Q58: генподряд | T58: эстакады ОЗХ | U58: монолит ПС и ОЗХ
C59: курс | N59: 89.79 | O59: 80 | Q59: 80 | U59: 91.5
C60: Стоимость контракта, млн руб. | O60: =243257433*O59/1000000 -> 19460.595 | Q60: =75531076.13*Q59/1000000 -> 6042.4861 | T60: 9163 | U60: =92336298*U59/1000000 -> 8448.7713
C61: Статус контракта | N61: подписан | O61: проект | Q61: проект | T61: проект | U61: проект
C62: Подготовка платежей | N62: 0 | O62: 23 млн $ на 29.07 | Q62: 23 млн $ на 22.07 | T62: август | U62: 23 млн $ на 29.07
C63: Статус ОБС-счета | N63: открыт Сбер | O63: нет | Q63: нет | T63: нет | U63: нет
C64: Статус ДБС | N64: получен | O64: нет | Q64: нет | T64: нет | U64: нет
C65: Статус БГ | N65: получена | O65: нет | Q65: нет | T65: нет | U65: нет
C67: риск возникновения ПДЗ в связи с окончанием сроков действия контрактов
C69: фин.потоки и контроль ПДЗ
